[{"iob":-0.082,"activity":0.003,"bolussnooze":0,"basaliob":-0.082,"netbasalinsulin":0.55,"hightempinsulin":0.8,"time":"2017-04-22T02:04:19.000Z"},{"iob":-0.144,"activity":0.0024,"bolussnooze":0,"basaliob":-0.144,"netbasalinsulin":0.4,"hightempinsulin":0.7,"time":"2017-04-22T02:09:19.000Z"},{"iob":-0.203,"activity":0.0019,"bolussnooze":0,"basaliob":-0.203,"netbasalinsulin":0.15,"hightempinsulin":0.5,"time":"2017-04-22T02:14:19.000Z"},{"iob":-0.261,"activity":0.0014,"bolussnooze":0,"basaliob":-0.261,"netbasalinsulin":-0.05,"hightempinsulin":0.35,"time":"2017-04-22T02:19:19.000Z"},{"iob":-0.266,"activity":0.001,"bolussnooze":0,"basaliob":-0.266,"netbasalinsulin":-0.05,"hightempinsulin":0.35,"time":"2017-04-22T02:24:19.000Z"},{"iob":-0.269,"activity":0.0006,"bolussnooze":0,"basaliob":-0.269,"netbasalinsulin":-0.05,"hightempinsulin":0.35,"time":"2017-04-22T02:29:19.000Z"},{"iob":-0.27,"activity":0.0002,"bolussnooze":0,"basaliob":-0.27,"netbasalinsulin":-0.05,"hightempinsulin":0.35,"time":"2017-04-22T02:34:19.000Z"},{"iob":-0.269,"activity":-0.0002,"bolussnooze":0,"basaliob":-0.269,"netbasalinsulin":-0.05,"hightempinsulin":0.35,"time":"2017-04-22T02:39:19.000Z"},{"iob":-0.265,"activity":-0.0007,"bolussnooze":0,"basaliob":-0.265,"netbasalinsulin":0,"hightempinsulin":0.35,"time":"2017-04-22T02:44:19.000Z"},{"iob":-0.26,"activity":-0.0011,"bolussnooze":0,"basaliob":-0.26,"netbasalinsulin":0,"hightempinsulin":0.35,"time":"2017-04-22T02:49:19.000Z"},{"iob":-0.252,"activity":-0.0015,"bolussnooze":0,"basaliob":-0.252,"netbasalinsulin":0,"hightempinsulin":0.35,"time":"2017-04-22T02:54:19.000Z"},{"iob":-0.242,"activity":-0.002,"bolussnooze":0,"basaliob":-0.242,"netbasalinsulin":0,"hightempinsulin":0.35,"time":"2017-04-22T02:59:19.000Z"},{"iob":-0.23,"activity":-0.0024,"bolussnooze":0,"basaliob":-0.23,"netbasalinsulin":0,"hightempinsulin":0.35,"time":"2017-04-22T03:04:19.000Z"},{"iob":-0.216,"activity":-0.0028,"bolussnooze":0,"basaliob":-0.216,"netbasalinsulin":-0.05,"hightempinsulin":0.3,"time":"2017-04-22T03:09:19.000Z"},{"iob":-0.201,"activity":-0.0031,"bolussnooze":0,"basaliob":-0.201,"netbasalinsulin":-0.05,"hightempinsulin":0.3,"time":"2017-04-22T03:14:19.000Z"},{"iob":-0.184,"activity":-0.0032,"bolussnooze":0,"basaliob":-0.184,"netbasalinsulin":-0.1,"hightempinsulin":0.25,"time":"2017-04-22T03:19:19.000Z"},{"iob":-0.168,"activity":-0.0033,"bolussnooze":0,"basaliob":-0.168,"netbasalinsulin":-0.15,"hightempinsulin":0.2,"time":"2017-04-22T03:24:19.000Z"},{"iob":-0.151,"activity":-0.0033,"bolussnooze":0,"basaliob":-0.151,"netbasalinsulin":-0.2,"hightempinsulin":0.15,"time":"2017-04-22T03:29:19.000Z"},{"iob":-0.135,"activity":-0.0032,"bolussnooze":0,"basaliob":-0.135,"netbasalinsulin":-0.25,"hightempinsulin":0.1,"time":"2017-04-22T03:34:19.000Z"},{"iob":-0.12,"activity":-0.003,"bolussnooze":0,"basaliob":-0.12,"netbasalinsulin":-0.3,"hightempinsulin":0.05,"time":"2017-04-22T03:39:19.000Z"},{"iob":-0.106,"activity":-0.0029,"bolussnooze":0,"basaliob":-0.106,"netbasalinsulin":-0.35,"hightempinsulin":0,"time":"2017-04-22T03:44:19.000Z"},{"iob":-0.092,"activity":-0.0027,"bolussnooze":0,"basaliob":-0.092,"netbasalinsulin":-0.35,"hightempinsulin":0,"time":"2017-04-22T03:49:19.000Z"},{"iob":-0.08,"activity":-0.0025,"bolussnooze":0,"basaliob":-0.08,"netbasalinsulin":-0.35,"hightempinsulin":0,"time":"2017-04-22T03:54:19.000Z"},{"iob":-0.068,"activity":-0.0023,"bolussnooze":0,"basaliob":-0.068,"netbasalinsulin":-0.35,"hightempinsulin":0,"time":"2017-04-22T03:59:19.000Z"},{"iob":-0.057,"activity":-0.0021,"bolussnooze":0,"basaliob":-0.057,"netbasalinsulin":-0.35,"hightempinsulin":0,"time":"2017-04-22T04:04:19.000Z"},{"iob":-0.048,"activity":-0.0019,"bolussnooze":0,"basaliob":-0.048,"netbasalinsulin":-0.35,"hightempinsulin":0,"time":"2017-04-22T04:09:19.000Z"},{"iob":-0.039,"activity":-0.0018,"bolussnooze":0,"basaliob":-0.039,"netbasalinsulin":-0.35,"hightempinsulin":0,"time":"2017-04-22T04:14:19.000Z"},{"iob":-0.031,"activity":-0.0016,"bolussnooze":0,"basaliob":-0.031,"netbasalinsulin":-0.35,"hightempinsulin":0,"time":"2017-04-22T04:19:19.000Z"},{"iob":-0.024,"activity":-0.0014,"bolussnooze":0,"basaliob":-0.024,"netbasalinsulin":-0.35,"hightempinsulin":0,"time":"2017-04-22T04:24:19.000Z"},{"iob":-0.018,"activity":-0.0012,"bolussnooze":0,"basaliob":-0.018,"netbasalinsulin":-0.35,"hightempinsulin":0,"time":"2017-04-22T04:29:19.000Z"},{"iob":-0.013,"activity":-0.001,"bolussnooze":0,"basaliob":-0.013,"netbasalinsulin":-0.35,"hightempinsulin":0,"time":"2017-04-22T04:34:19.000Z"},{"iob":-0.009,"activity":-0.0008,"bolussnooze":0,"basaliob":-0.009,"netbasalinsulin":-0.35,"hightempinsulin":0,"time":"2017-04-22T04:39:19.000Z"},{"iob":-0.005,"activity":-0.0006,"bolussnooze":0,"basaliob":-0.005,"netbasalinsulin":-0.35,"hightempinsulin":0,"time":"2017-04-22T04:44:19.000Z"},{"iob":-0.003,"activity":-0.0005,"bolussnooze":0,"basaliob":-0.003,"netbasalinsulin":-0.3,"hightempinsulin":0,"time":"2017-04-22T04:49:19.000Z"},{"iob":-0.002,"activity":-0.0003,"bolussnooze":0,"basaliob":-0.002,"netbasalinsulin":-0.25,"hightempinsulin":0,"time":"2017-04-22T04:54:19.000Z"},{"iob":-0.001,"activity":-0.0002,"bolussnooze":0,"basaliob":-0.001,"netbasalinsulin":-0.2,"hightempinsulin":0,"time":"2017-04-22T04:59:19.000Z"},{"iob":0,"activity":-0.0001,"bolussnooze":0,"basaliob":0,"netbasalinsulin":-0.15,"hightempinsulin":0,"time":"2017-04-22T05:04:19.000Z"},{"iob":0,"activity":0,"bolussnooze":0,"basaliob":0,"netbasalinsulin":-0.1,"hightempinsulin":0,"time":"2017-04-22T05:09:19.000Z"},{"iob":0,"activity":0,"bolussnooze":0,"basaliob":0,"netbasalinsulin":-0.05,"hightempinsulin":0,"time":"2017-04-22T05:14:19.000Z"},{"iob":0,"activity":0,"bolussnooze":0,"basaliob":0,"netbasalinsulin":0,"hightempinsulin":0,"time":"2017-04-22T05:19:19.000Z"},{"iob":0,"activity":0,"bolussnooze":0,"basaliob":0,"netbasalinsulin":0,"hightempinsulin":0,"time":"2017-04-22T05:24:19.000Z"},{"iob":0,"activity":0,"bolussnooze":0,"basaliob":0,"netbasalinsulin":0,"hightempinsulin":0,"time":"2017-04-22T05:29:19.000Z"}]
