[{"iob":1.111,"activity":-0.0014,"bolussnooze":1.174,"basaliob":-0.154,"netbasalinsulin":-0.5,"hightempinsulin":0.35,"time":"2017-03-27T14:12:17.000Z"},{"iob":1.111,"activity":-0.0001,"bolussnooze":1.095,"basaliob":-0.132,"netbasalinsulin":-0.55,"hightempinsulin":0.3,"time":"2017-03-27T14:17:17.000Z"},{"iob":1.105,"activity":0.0012,"bolussnooze":0.996,"basaliob":-0.112,"netbasalinsulin":-0.65,"hightempinsulin":0.2,"time":"2017-03-27T14:22:17.000Z"},{"iob":1.092,"activity":0.0026,"bolussnooze":0.878,"basaliob":-0.095,"netbasalinsulin":-0.7,"hightempinsulin":0.15,"time":"2017-03-27T14:27:17.000Z"},{"iob":1.072,"activity":0.004,"bolussnooze":0.741,"basaliob":-0.079,"netbasalinsulin":-0.75,"hightempinsulin":0.1,"time":"2017-03-27T14:32:17.000Z"},{"iob":1.045,"activity":0.0055,"bolussnooze":0.604,"basaliob":-0.066,"netbasalinsulin":-0.7,"hightempinsulin":0.1,"time":"2017-03-27T14:37:17.000Z"},{"iob":1.01,"activity":0.0068,"bolussnooze":0.482,"basaliob":-0.056,"netbasalinsulin":-0.65,"hightempinsulin":0.1,"time":"2017-03-27T14:42:17.000Z"},{"iob":0.97,"activity":0.0081,"bolussnooze":0.374,"basaliob":-0.046,"netbasalinsulin":-0.6,"hightempinsulin":0.1,"time":"2017-03-27T14:47:17.000Z"},{"iob":0.923,"activity":0.0094,"bolussnooze":0.279,"basaliob":-0.038,"netbasalinsulin":-0.55,"hightempinsulin":0.1,"time":"2017-03-27T14:52:17.000Z"},{"iob":0.87,"activity":0.0105,"bolussnooze":0.198,"basaliob":-0.032,"netbasalinsulin":-0.5,"hightempinsulin":0.1,"time":"2017-03-27T14:57:17.000Z"},{"iob":0.811,"activity":0.0117,"bolussnooze":0.131,"basaliob":-0.026,"netbasalinsulin":-0.45,"hightempinsulin":0.1,"time":"2017-03-27T15:02:17.000Z"},{"iob":0.747,"activity":0.0128,"bolussnooze":0.078,"basaliob":-0.021,"netbasalinsulin":-0.4,"hightempinsulin":0.1,"time":"2017-03-27T15:07:17.000Z"},{"iob":0.68,"activity":0.0133,"bolussnooze":0.039,"basaliob":-0.016,"netbasalinsulin":-0.35,"hightempinsulin":0.1,"time":"2017-03-27T15:12:17.000Z"},{"iob":0.616,"activity":0.0128,"bolussnooze":0.013,"basaliob":-0.013,"netbasalinsulin":-0.3,"hightempinsulin":0.1,"time":"2017-03-27T15:17:17.000Z"},{"iob":0.555,"activity":0.0122,"bolussnooze":0.001,"basaliob":-0.01,"netbasalinsulin":-0.3,"hightempinsulin":0.1,"time":"2017-03-27T15:22:17.000Z"},{"iob":0.496,"activity":0.0117,"bolussnooze":0,"basaliob":-0.008,"netbasalinsulin":-0.3,"hightempinsulin":0.1,"time":"2017-03-27T15:27:17.000Z"},{"iob":0.441,"activity":0.0111,"bolussnooze":0,"basaliob":-0.006,"netbasalinsulin":-0.25,"hightempinsulin":0.1,"time":"2017-03-27T15:32:17.000Z"},{"iob":0.388,"activity":0.0106,"bolussnooze":0,"basaliob":-0.005,"netbasalinsulin":-0.2,"hightempinsulin":0.1,"time":"2017-03-27T15:37:17.000Z"},{"iob":0.338,"activity":0.01,"bolussnooze":0,"basaliob":-0.005,"netbasalinsulin":-0.15,"hightempinsulin":0.1,"time":"2017-03-27T15:42:17.000Z"},{"iob":0.291,"activity":0.0094,"bolussnooze":0,"basaliob":-0.005,"netbasalinsulin":-0.1,"hightempinsulin":0.1,"time":"2017-03-27T15:47:17.000Z"},{"iob":0.247,"activity":0.0087,"bolussnooze":0,"basaliob":-0.005,"netbasalinsulin":-0.05,"hightempinsulin":0.1,"time":"2017-03-27T15:52:17.000Z"},{"iob":0.207,"activity":0.008,"bolussnooze":0,"basaliob":-0.005,"netbasalinsulin":0.05,"hightempinsulin":0.1,"time":"2017-03-27T15:57:17.000Z"},{"iob":0.171,"activity":0.0073,"bolussnooze":0,"basaliob":-0.005,"netbasalinsulin":0.05,"hightempinsulin":0.1,"time":"2017-03-27T16:02:17.000Z"},{"iob":0.138,"activity":0.0066,"bolussnooze":0,"basaliob":-0.005,"netbasalinsulin":0.05,"hightempinsulin":0.1,"time":"2017-03-27T16:07:17.000Z"},{"iob":0.109,"activity":0.0059,"bolussnooze":0,"basaliob":-0.004,"netbasalinsulin":0.05,"hightempinsulin":0.1,"time":"2017-03-27T16:12:17.000Z"},{"iob":0.083,"activity":0.0052,"bolussnooze":0,"basaliob":-0.004,"netbasalinsulin":0.05,"hightempinsulin":0.1,"time":"2017-03-27T16:17:17.000Z"},{"iob":0.061,"activity":0.0044,"bolussnooze":0,"basaliob":-0.003,"netbasalinsulin":0.05,"hightempinsulin":0.1,"time":"2017-03-27T16:22:17.000Z"},{"iob":0.042,"activity":0.0037,"bolussnooze":0,"basaliob":-0.003,"netbasalinsulin":0.05,"hightempinsulin":0.1,"time":"2017-03-27T16:27:17.000Z"},{"iob":0.027,"activity":0.003,"bolussnooze":0,"basaliob":-0.002,"netbasalinsulin":0,"hightempinsulin":0.05,"time":"2017-03-27T16:32:17.000Z"},{"iob":0.015,"activity":0.0024,"bolussnooze":0,"basaliob":-0.001,"netbasalinsulin":-0.05,"hightempinsulin":0,"time":"2017-03-27T16:37:17.000Z"},{"iob":0.007,"activity":0.0017,"bolussnooze":0,"basaliob":-0.001,"netbasalinsulin":-0.05,"hightempinsulin":0,"time":"2017-03-27T16:42:17.000Z"},{"iob":0.002,"activity":0.001,"bolussnooze":0,"basaliob":0,"netbasalinsulin":-0.05,"hightempinsulin":0,"time":"2017-03-27T16:47:17.000Z"},{"iob":0,"activity":0.0004,"bolussnooze":0,"basaliob":0,"netbasalinsulin":-0.05,"hightempinsulin":0,"time":"2017-03-27T16:52:17.000Z"},{"iob":0,"activity":0,"bolussnooze":0,"basaliob":0,"netbasalinsulin":-0.05,"hightempinsulin":0,"time":"2017-03-27T16:57:17.000Z"},{"iob":0,"activity":0,"bolussnooze":0,"basaliob":0,"netbasalinsulin":0,"hightempinsulin":0,"time":"2017-03-27T17:02:17.000Z"},{"iob":0,"activity":0,"bolussnooze":0,"basaliob":0,"netbasalinsulin":0,"hightempinsulin":0,"time":"2017-03-27T17:07:17.000Z"},{"iob":0,"activity":0,"bolussnooze":0,"basaliob":0,"netbasalinsulin":0,"hightempinsulin":0,"time":"2017-03-27T17:12:17.000Z"},{"iob":0,"activity":0,"bolussnooze":0,"basaliob":0,"netbasalinsulin":0,"hightempinsulin":0,"time":"2017-03-27T17:17:17.000Z"},{"iob":0,"activity":0,"bolussnooze":0,"basaliob":0,"netbasalinsulin":0,"hightempinsulin":0,"time":"2017-03-27T17:22:17.000Z"},{"iob":0,"activity":0,"bolussnooze":0,"basaliob":0,"netbasalinsulin":0,"hightempinsulin":0,"time":"2017-03-27T17:27:17.000Z"},{"iob":0,"activity":0,"bolussnooze":0,"basaliob":0,"netbasalinsulin":0,"hightempinsulin":0,"time":"2017-03-27T17:32:17.000Z"},{"iob":0,"activity":0,"bolussnooze":0,"basaliob":0,"netbasalinsulin":0,"hightempinsulin":0,"time":"2017-03-27T17:37:17.000Z"}]
