{
  "bg": 45, 
  "temp": "absolute", 
  "snoozeBG": 124, 
  "predBGs": {
    "COB": [
      45, 
      51, 
      57, 
      64, 
      72, 
      80, 
      88, 
      97, 
      106, 
      116, 
      126, 
      136, 
      146, 
      156, 
      166, 
      176, 
      186, 
      196, 
      206, 
      215, 
      224, 
      233, 
      241, 
      249, 
      256, 
      263, 
      269, 
      275, 
      281, 
      286, 
      291, 
      296, 
      301, 
      305, 
      309, 
      313, 
      316, 
      320, 
      323, 
      326, 
      330, 
      333, 
      336
    ], 
    "aCOB": [
      45, 
      57, 
      69, 
      82, 
      94, 
      108, 
      122, 
      136, 
      150, 
      164, 
      179, 
      194, 
      208, 
      223, 
      237, 
      251, 
      265, 
      279, 
      292, 
      305, 
      318, 
      330, 
      341, 
      352, 
      362, 
      372, 
      381, 
      390, 
      398, 
      401
    ], 
    "IOB": [
      45, 
      51, 
      56, 
      62, 
      69, 
      75, 
      82, 
      88, 
      95, 
      102, 
      109, 
      115, 
      122, 
      128, 
      135, 
      141, 
      148, 
      154, 
      160, 
      166, 
      171, 
      176, 
      181, 
      185, 
      189, 
      193, 
      196, 
      198, 
      201, 
      203, 
      205, 
      206, 
      207, 
      208, 
      209, 
      210, 
      210, 
      211
    ]
  }, 
  "reason": "COB: 40, Dev: -14, BGI: 1.94, ISF: 90, Target: 100; BG 45<75, but 28m left and 0 ~ req 0U/hr: no action required", 
  "COB": 40, 
  "eventualBG": 336, 
  "tick": "+6", 
  "IOB": -1.032
}