{
  "bg": 65, 
  "temp": "absolute", 
  "snoozeBG": 109, 
  "predBGs": {
    "IOB": [
      65, 
      63, 
      62, 
      62, 
      62, 
      63, 
      64, 
      66, 
      69, 
      72, 
      76, 
      80, 
      85, 
      90, 
      94, 
      99, 
      104, 
      108, 
      112, 
      116, 
      119, 
      122, 
      125, 
      128, 
      130, 
      132, 
      134, 
      136, 
      137, 
      138, 
      139, 
      140, 
      141, 
      141, 
      142, 
      142, 
      142, 
      142, 
      142, 
      143
    ]
  }, 
  "reason": "COB: 0, Dev: -22, BGI: 1.79, ISF: 102, Target: 103; BG 65<77, but 22m left and 0 ~ req 0U/hr: no action required", 
  "COB": 0, 
  "eventualBG": 109, 
  "tick": -2, 
  "IOB": -0.695
}