[
  {
    "created_at": "2017-03-30T10:35:07.815Z", 
    "mmtune": {
      "scanDetails": [
        [
          null, 
          0, 
          -80.8
        ]
      ], 
      "timestamp": "2017-03-30T10:34:51.512Z"
    }, 
    "pump": {
      "battery": {
        "status": "normal", 
        "voltage": 1.38
      }, 
      "status": {
        "status": "normal", 
        "timestamp": "2017-03-30T10:30:42.239Z", 
        "bolusing": false, 
        "suspended": false
      }, 
      "reservoir": 110.95, 
      "clock": "2017-03-30T03:30:29-07:00"
    }, 
    "openaps": {
      "suggested": {
        "bg": 99, 
        "temp": "absolute", 
        "snoozeBG": 94, 
        "timestamp": "2017-03-30T10:34:43.341Z", 
        "predBGs": {
          "IOB": [
            99, 
            96, 
            94, 
            91, 
            90, 
            88, 
            87, 
            86, 
            85, 
            85, 
            84, 
            84, 
            85, 
            85, 
            85, 
            85, 
            86, 
            86, 
            86, 
            86, 
            87, 
            87, 
            87, 
            88, 
            88, 
            88, 
            89, 
            89, 
            89, 
            89, 
            89, 
            89, 
            89, 
            89, 
            89, 
            89, 
            88
          ]
        }, 
        "reason": "COB: 0, Dev: -8, BGI: -1.6, ISF: 86, Target: 96; Eventual BG 94 < 96, temp 0.55 ~< req 0.55U/hr", 
        "COB": 0, 
        "eventualBG": 94, 
        "tick": -2, 
        "IOB": -0.029
      }, 
      "iob": {
        "netbasalinsulin": 0.45, 
        "timestamp": "2017-03-30T10:30:29.000Z", 
        "activity": 0.0037, 
        "basaliob": -0.029, 
        "hightempinsulin": 0.85, 
        "bolussnooze": 0, 
        "iob": -0.029
      }, 
      "enacted": {
        "bg": 117, 
        "temp": "absolute", 
        "snoozeBG": 84, 
        "recieved": true, 
        "reason": "COB: 0, Dev: -12, BGI: -1.94, ISF: 86, Target: 96; Eventual BG 84 < 96, setting 0.275U/hr", 
        "rate": 0.575, 
        "COB": 0, 
        "eventualBG": 84, 
        "timestamp": "2017-03-30T10:07:55.285Z", 
        "duration": 23, 
        "tick": -5, 
        "IOB": 0.243
      }
    }, 
    "uploader": {
      "battery": 66, 
      "batteryVoltage": 3844
    }, 
    "device": "openaps://indy-ex2", 
    "_id": "58dcdf5bc402f060d03610d7"
  }
]