{
  "bg": 113, 
  "temp": "absolute", 
  "snoozeBG": 120, 
  "recieved": true, 
  "predBGs": {
    "IOB": [
      113, 
      112, 
      112, 
      112, 
      111, 
      111, 
      111, 
      112, 
      112, 
      112, 
      113, 
      114, 
      115, 
      116, 
      117, 
      118, 
      119, 
      121, 
      122, 
      123, 
      125, 
      126, 
      127, 
      128, 
      130, 
      130, 
      131, 
      132, 
      133, 
      133, 
      134, 
      134, 
      135, 
      135, 
      135, 
      136
    ]
  }, 
  "reason": "COB: 0, Dev: 0, BGI: -0.53, ISF: 107, Target: 105; Eventual BG 120 >= 105, temp 0.225<0.675U/hr", 
  "rate": 0.675, 
  "COB": 0, 
  "eventualBG": 120, 
  "timestamp": "2017-05-02T06:15:24.512929", 
  "duration": 30, 
  "tick": "+3", 
  "IOB": -0.069
}