[
  {
    "trend_arrow": "FLAT", 
    "display_time": "2017-03-21T20:05:33-07:00", 
    "noise": 1, 
    "system_time": "2017-03-22T03:04:35-07:00", 
    "direction": "Flat", 
    "sgv": 148, 
    "dateString": "2017-03-21T20:05:33-07:00", 
    "date": 1490151933000, 
    "unfiltered": 147872, 
    "filtered": 150880, 
    "device": "openaps://indy-e1/cgm", 
    "rssi": 931, 
    "_id": "58d1ea9665110bbfc195de2d", 
    "type": "sgv", 
    "glucose": 148
  }, 
  {
    "trend_arrow": "FLAT", 
    "display_time": "2017-03-21T20:05:27-07:00", 
    "noise": 1, 
    "system_time": "2017-03-22T01:55:36-07:00", 
    "direction": "Flat", 
    "sgv": 148, 
    "dateString": "2017-03-21T20:05:27-07:00", 
    "device": "openaps://indy-ex2/cgm", 
    "unfiltered": 147872, 
    "rssi": 185, 
    "date": 1490151927000, 
    "filtered": 150880, 
    "_id": "58d1ea9a65110bbfc195de2e", 
    "type": "sgv", 
    "glucose": 148
  }, 
  {
    "trend_arrow": "FLAT", 
    "display_time": "2017-03-21T20:00:32-07:00", 
    "noise": 1, 
    "system_time": "2017-03-22T02:59:33-07:00", 
    "direction": "Flat", 
    "sgv": 150, 
    "dateString": "2017-03-21T20:00:32-07:00", 
    "date": 1490151632000, 
    "unfiltered": 150048, 
    "filtered": 153408, 
    "device": "openaps://indy-e1/cgm", 
    "rssi": 171, 
    "_id": "58d1e91d65110bbfc195de2b", 
    "type": "sgv", 
    "glucose": 150
  }, 
  {
    "trend_arrow": "FLAT", 
    "display_time": "2017-03-21T20:00:27-07:00", 
    "noise": 1, 
    "system_time": "2017-03-22T01:50:36-07:00", 
    "direction": "Flat", 
    "sgv": 150, 
    "dateString": "2017-03-21T20:00:27-07:00", 
    "date": 1490151627000, 
    "unfiltered": 150048, 
    "filtered": 153408, 
    "device": "openaps://indy-ex2/cgm", 
    "rssi": 191, 
    "_id": "58d1e94765110bbfc195de2c", 
    "type": "sgv", 
    "glucose": 150
  }, 
  {
    "trend_arrow": "FLAT", 
    "display_time": "2017-03-21T19:55:32-07:00", 
    "noise": 1, 
    "system_time": "2017-03-22T02:54:33-07:00", 
    "direction": "Flat", 
    "sgv": 153, 
    "dateString": "2017-03-21T19:55:32-07:00", 
    "date": 1490151332000, 
    "unfiltered": 152288, 
    "filtered": 156544, 
    "device": "openaps://indy-e1/cgm", 
    "rssi": 173, 
    "_id": "58d1e7ff65110bbfc195de29", 
    "type": "sgv", 
    "glucose": 153
  }, 
  {
    "trend_arrow": "FLAT", 
    "display_time": "2017-03-21T19:55:27-07:00", 
    "noise": 1, 
    "system_time": "2017-03-22T01:45:36-07:00", 
    "direction": "Flat", 
    "sgv": 153, 
    "dateString": "2017-03-21T19:55:27-07:00", 
    "date": 1490151327000, 
    "unfiltered": 152288, 
    "filtered": 156544, 
    "device": "openaps://indy-ex2/cgm", 
    "rssi": 180, 
    "_id": "58d1e80865110bbfc195de2a", 
    "type": "sgv", 
    "glucose": 153
  }, 
  {
    "trend_arrow": "FLAT", 
    "display_time": "2017-03-21T19:50:32-07:00", 
    "noise": 1, 
    "system_time": "2017-03-22T02:49:33-07:00", 
    "direction": "Flat", 
    "sgv": 156, 
    "dateString": "2017-03-21T19:50:32-07:00", 
    "date": 1490151032000, 
    "unfiltered": 154592, 
    "filtered": 160160, 
    "device": "openaps://indy-e1/cgm", 
    "rssi": 168, 
    "_id": "58d1e6ad65110bbfc195de25", 
    "type": "sgv", 
    "glucose": 156
  }, 
  {
    "trend_arrow": "FLAT", 
    "display_time": "2017-03-21T19:50:27-07:00", 
    "noise": 1, 
    "system_time": "2017-03-22T01:40:36-07:00", 
    "direction": "Flat", 
    "sgv": 156, 
    "dateString": "2017-03-21T19:50:27-07:00", 
    "date": 1490151027000, 
    "unfiltered": 154592, 
    "filtered": 160160, 
    "device": "openaps://indy-ex2/cgm", 
    "rssi": 193, 
    "_id": "58d1e6cf65110bbfc195de26", 
    "type": "sgv", 
    "glucose": 156
  }, 
  {
    "trend_arrow": "FLAT", 
    "display_time": "2017-03-21T19:45:32-07:00", 
    "noise": 1, 
    "system_time": "2017-03-22T02:44:33-07:00", 
    "direction": "Flat", 
    "sgv": 160, 
    "dateString": "2017-03-21T19:45:32-07:00", 
    "date": 1490150732000, 
    "unfiltered": 157696, 
    "filtered": 163904, 
    "device": "openaps://indy-e1/cgm", 
    "rssi": 165, 
    "_id": "58d1e5d265110bbfc195de23", 
    "type": "sgv", 
    "glucose": 160
  }, 
  {
    "trend_arrow": "FLAT", 
    "display_time": "2017-03-21T19:45:27-07:00", 
    "noise": 1, 
    "system_time": "2017-03-22T01:35:36-07:00", 
    "direction": "Flat", 
    "sgv": 160, 
    "dateString": "2017-03-21T19:45:27-07:00", 
    "date": 1490150727000, 
    "unfiltered": 157696, 
    "filtered": 163904, 
    "device": "openaps://indy-ex2/cgm", 
    "rssi": 185, 
    "_id": "58d1e5d865110bbfc195de24", 
    "type": "sgv", 
    "glucose": 160
  }, 
  {
    "trend_arrow": "FLAT", 
    "display_time": "2017-03-21T19:40:32-07:00", 
    "noise": 1, 
    "system_time": "2017-03-22T02:39:33-07:00", 
    "direction": "Flat", 
    "sgv": 167, 
    "dateString": "2017-03-21T19:40:32-07:00", 
    "date": 1490150432000, 
    "unfiltered": 162816, 
    "filtered": 167008, 
    "device": "openaps://indy-e1/cgm", 
    "rssi": 171, 
    "_id": "58d1e45a65110bbfc195de20", 
    "type": "sgv", 
    "glucose": 167
  }, 
  {
    "trend_arrow": "FLAT", 
    "display_time": "2017-03-21T19:40:27-07:00", 
    "noise": 1, 
    "system_time": "2017-03-22T01:30:36-07:00", 
    "direction": "Flat", 
    "sgv": 167, 
    "dateString": "2017-03-21T19:40:27-07:00", 
    "date": 1490150427000, 
    "unfiltered": 162816, 
    "filtered": 167008, 
    "device": "openaps://indy-ex2/cgm", 
    "rssi": 184, 
    "_id": "58d1e47d65110bbfc195de21", 
    "type": "sgv", 
    "glucose": 167
  }, 
  {
    "trend_arrow": "FLAT", 
    "display_time": "2017-03-21T19:35:32-07:00", 
    "noise": 1, 
    "system_time": "2017-03-22T02:34:34-07:00", 
    "direction": "Flat", 
    "sgv": 167, 
    "dateString": "2017-03-21T19:35:32-07:00", 
    "date": 1490150132000, 
    "unfiltered": 163424, 
    "filtered": 168928, 
    "device": "openaps://indy-e1/cgm", 
    "rssi": 423, 
    "_id": "58d1e34765110bbfc195de1d", 
    "type": "sgv", 
    "glucose": 167
  }, 
  {
    "trend_arrow": "FLAT", 
    "display_time": "2017-03-21T19:35:28-07:00", 
    "noise": 1, 
    "system_time": "2017-03-22T01:25:36-07:00", 
    "direction": "Flat", 
    "sgv": 167, 
    "dateString": "2017-03-21T19:35:28-07:00", 
    "date": 1490150128000, 
    "unfiltered": 163424, 
    "filtered": 168928, 
    "device": "openaps://indy-ex2/cgm", 
    "rssi": 447, 
    "_id": "58d1e36165110bbfc195de1e", 
    "type": "sgv", 
    "glucose": 167
  }, 
  {
    "trend_arrow": "FLAT", 
    "display_time": "2017-03-21T19:30:32-07:00", 
    "noise": 1, 
    "system_time": "2017-03-22T02:29:33-07:00", 
    "direction": "Flat", 
    "sgv": 175, 
    "dateString": "2017-03-21T19:30:32-07:00", 
    "date": 1490149832000, 
    "unfiltered": 169568, 
    "filtered": 169280, 
    "device": "openaps://indy-e1/cgm", 
    "rssi": 168, 
    "_id": "58d1e20865110bbfc195de1b", 
    "type": "sgv", 
    "glucose": 175
  }, 
  {
    "trend_arrow": "FLAT", 
    "display_time": "2017-03-21T19:30:27-07:00", 
    "noise": 1, 
    "system_time": "2017-03-22T01:20:36-07:00", 
    "direction": "Flat", 
    "sgv": 175, 
    "dateString": "2017-03-21T19:30:27-07:00", 
    "date": 1490149827000, 
    "unfiltered": 169568, 
    "filtered": 169280, 
    "device": "openaps://indy-ex2/cgm", 
    "rssi": 181, 
    "_id": "58d1e21c65110bbfc195de1c", 
    "type": "sgv", 
    "glucose": 175
  }, 
  {
    "trend_arrow": "FLAT", 
    "display_time": "2017-03-21T19:25:32-07:00", 
    "noise": 1, 
    "system_time": "2017-03-22T02:24:34-07:00", 
    "direction": "Flat", 
    "sgv": 173, 
    "dateString": "2017-03-21T19:25:32-07:00", 
    "date": 1490149532000, 
    "unfiltered": 168128, 
    "filtered": 168416, 
    "device": "openaps://indy-e1/cgm", 
    "rssi": 416, 
    "_id": "58d1e0c565110bbfc195de18", 
    "type": "sgv", 
    "glucose": 173
  }, 
  {
    "trend_arrow": "FLAT", 
    "display_time": "2017-03-21T19:25:27-07:00", 
    "noise": 1, 
    "system_time": "2017-03-22T01:15:36-07:00", 
    "direction": "Flat", 
    "sgv": 173, 
    "dateString": "2017-03-21T19:25:27-07:00", 
    "date": 1490149527000, 
    "unfiltered": 168128, 
    "filtered": 168416, 
    "device": "openaps://indy-ex2/cgm", 
    "rssi": 178, 
    "_id": "58d1e13765110bbfc195de19", 
    "type": "sgv", 
    "glucose": 173
  }, 
  {
    "trend_arrow": "FLAT", 
    "display_time": "2017-03-21T19:20:28-07:00", 
    "noise": 1, 
    "system_time": "2017-03-22T01:10:36-07:00", 
    "direction": "Flat", 
    "sgv": 177, 
    "dateString": "2017-03-21T19:20:28-07:00", 
    "date": 1490149228000, 
    "unfiltered": 170976, 
    "filtered": 166880, 
    "device": "openaps://indy-ex2/cgm", 
    "rssi": 204, 
    "_id": "58d1e00565110bbfc195de17", 
    "type": "sgv", 
    "glucose": 177
  }, 
  {
    "trend_arrow": "FLAT", 
    "display_time": "2017-03-21T19:15:32-07:00", 
    "noise": 1, 
    "system_time": "2017-03-22T02:14:34-07:00", 
    "direction": "Flat", 
    "sgv": 172, 
    "dateString": "2017-03-21T19:15:32-07:00", 
    "date": 1490148932000, 
    "unfiltered": 166944, 
    "filtered": 164256, 
    "device": "openaps://indy-e1/cgm", 
    "rssi": 416, 
    "_id": "58d1de7d65110bbfc195de14", 
    "type": "sgv", 
    "glucose": 172
  }, 
  {
    "trend_arrow": "FLAT", 
    "display_time": "2017-03-21T19:15:27-07:00", 
    "noise": 1, 
    "system_time": "2017-03-22T01:05:36-07:00", 
    "direction": "Flat", 
    "sgv": 172, 
    "dateString": "2017-03-21T19:15:27-07:00", 
    "date": 1490148927000, 
    "unfiltered": 166944, 
    "filtered": 164256, 
    "device": "openaps://indy-ex2/cgm", 
    "rssi": 172, 
    "_id": "58d1de9965110bbfc195de15", 
    "type": "sgv", 
    "glucose": 172
  }, 
  {
    "trend_arrow": "FLAT", 
    "display_time": "2017-03-21T19:10:32-07:00", 
    "noise": 1, 
    "system_time": "2017-03-22T02:09:33-07:00", 
    "direction": "Flat", 
    "sgv": 169, 
    "dateString": "2017-03-21T19:10:32-07:00", 
    "date": 1490148632000, 
    "unfiltered": 164608, 
    "filtered": 160320, 
    "device": "openaps://indy-e1/cgm", 
    "rssi": 172, 
    "_id": "58d1dd4d65110bbfc195de12", 
    "type": "sgv", 
    "glucose": 169
  }, 
  {
    "trend_arrow": "FLAT", 
    "display_time": "2017-03-21T19:10:27-07:00", 
    "noise": 1, 
    "system_time": "2017-03-22T01:00:36-07:00", 
    "direction": "Flat", 
    "sgv": 169, 
    "dateString": "2017-03-21T19:10:27-07:00", 
    "date": 1490148627000, 
    "unfiltered": 164608, 
    "filtered": 160320, 
    "device": "openaps://indy-ex2/cgm", 
    "rssi": 184, 
    "_id": "58d1dda965110bbfc195de13", 
    "type": "sgv", 
    "glucose": 169
  }, 
  {
    "trend_arrow": "45_UP", 
    "display_time": "2017-03-21T19:05:32-07:00", 
    "noise": 1, 
    "system_time": "2017-03-22T02:04:34-07:00", 
    "direction": "FortyFiveUp", 
    "sgv": 167, 
    "dateString": "2017-03-21T19:05:32-07:00", 
    "date": 1490148332000, 
    "unfiltered": 163200, 
    "filtered": 155328, 
    "device": "openaps://indy-e1/cgm", 
    "rssi": 419, 
    "_id": "58d1dc2165110bbfc195de0f", 
    "type": "sgv", 
    "glucose": 167
  }, 
  {
    "trend_arrow": "45_UP", 
    "display_time": "2017-03-21T19:05:27-07:00", 
    "noise": 1, 
    "system_time": "2017-03-22T00:55:36-07:00", 
    "direction": "FortyFiveUp", 
    "sgv": 167, 
    "dateString": "2017-03-21T19:05:27-07:00", 
    "date": 1490148327000, 
    "unfiltered": 163200, 
    "filtered": 155328, 
    "device": "openaps://indy-ex2/cgm", 
    "rssi": 186, 
    "_id": "58d1dc9665110bbfc195de11", 
    "type": "sgv", 
    "glucose": 167
  }, 
  {
    "trend_arrow": "FLAT", 
    "display_time": "2017-03-21T19:00:32-07:00", 
    "noise": 1, 
    "system_time": "2017-03-22T01:59:33-07:00", 
    "direction": "Flat", 
    "sgv": 163, 
    "dateString": "2017-03-21T19:00:32-07:00", 
    "date": 1490148032000, 
    "unfiltered": 159616, 
    "filtered": 150496, 
    "device": "openaps://indy-e1/cgm", 
    "rssi": 175, 
    "_id": "58d1dadd65110bbfc195de0d", 
    "type": "sgv", 
    "glucose": 163
  }, 
  {
    "trend_arrow": "45_UP", 
    "display_time": "2017-03-21T19:00:27-07:00", 
    "noise": 1, 
    "system_time": "2017-03-22T00:50:36-07:00", 
    "direction": "FortyFiveUp", 
    "sgv": 163, 
    "dateString": "2017-03-21T19:00:27-07:00", 
    "date": 1490148027000, 
    "unfiltered": 159616, 
    "filtered": 150496, 
    "device": "openaps://indy-ex2/cgm", 
    "rssi": 194, 
    "_id": "58d1db6a65110bbfc195de0e", 
    "type": "sgv", 
    "glucose": 163
  }, 
  {
    "trend_arrow": "FLAT", 
    "display_time": "2017-03-21T18:55:27-07:00", 
    "noise": 1, 
    "system_time": "2017-03-22T00:45:36-07:00", 
    "direction": "Flat", 
    "sgv": 154, 
    "dateString": "2017-03-21T18:55:27-07:00", 
    "date": 1490147727000, 
    "unfiltered": 153056, 
    "filtered": 146784, 
    "device": "openaps://indy-ex2/cgm", 
    "rssi": 181, 
    "_id": "58d1d9d365110bbfc195de0c", 
    "type": "sgv", 
    "glucose": 154
  }, 
  {
    "trend_arrow": "FLAT", 
    "display_time": "2017-03-21T18:50:32-07:00", 
    "noise": 1, 
    "system_time": "2017-03-22T01:49:33-07:00", 
    "direction": "Flat", 
    "sgv": 148, 
    "dateString": "2017-03-21T18:50:32-07:00", 
    "date": 1490147432000, 
    "unfiltered": 148288, 
    "filtered": 144128, 
    "device": "openaps://indy-e1/cgm", 
    "rssi": 178, 
    "_id": "58d1d8ac65110bbfc195de09", 
    "type": "sgv", 
    "glucose": 148
  }, 
  {
    "trend_arrow": "FLAT", 
    "display_time": "2017-03-21T18:50:28-07:00", 
    "noise": 1, 
    "system_time": "2017-03-22T00:40:37-07:00", 
    "direction": "Flat", 
    "sgv": 148, 
    "dateString": "2017-03-21T18:50:28-07:00", 
    "date": 1490147428000, 
    "unfiltered": 148288, 
    "filtered": 144128, 
    "device": "openaps://indy-ex2/cgm", 
    "rssi": 442, 
    "_id": "58d1d8fb65110bbfc195de0a", 
    "type": "sgv", 
    "glucose": 148
  }, 
  {
    "trend_arrow": "FLAT", 
    "display_time": "2017-03-21T18:45:32-07:00", 
    "noise": 1, 
    "system_time": "2017-03-22T01:44:33-07:00", 
    "direction": "Flat", 
    "sgv": 144, 
    "dateString": "2017-03-21T18:45:32-07:00", 
    "date": 1490147132000, 
    "unfiltered": 144960, 
    "filtered": 142016, 
    "device": "openaps://indy-e1/cgm", 
    "rssi": 168, 
    "_id": "58d1d77765110bbfc195de08", 
    "type": "sgv", 
    "glucose": 144
  }, 
  {
    "trend_arrow": "FLAT", 
    "display_time": "2017-03-21T18:45:28-07:00", 
    "noise": 1, 
    "system_time": "2017-03-22T00:35:36-07:00", 
    "direction": "Flat", 
    "sgv": 144, 
    "dateString": "2017-03-21T18:45:28-07:00", 
    "date": 1490147128000, 
    "unfiltered": 144960, 
    "filtered": 142016, 
    "device": "openaps://indy-ex2/cgm", 
    "rssi": 183, 
    "_id": "58d1d8fb65110bbfc195de0b", 
    "type": "sgv", 
    "glucose": 144
  }, 
  {
    "trend_arrow": "FLAT", 
    "display_time": "2017-03-21T18:40:32-07:00", 
    "noise": 1, 
    "system_time": "2017-03-22T01:39:33-07:00", 
    "direction": "Flat", 
    "sgv": 142, 
    "dateString": "2017-03-21T18:40:32-07:00", 
    "date": 1490146832000, 
    "unfiltered": 143488, 
    "filtered": 140000, 
    "device": "openaps://indy-e1/cgm", 
    "rssi": 182, 
    "_id": "58d1d64565110bbfc195de06", 
    "type": "sgv", 
    "glucose": 142
  }, 
  {
    "trend_arrow": "FLAT", 
    "display_time": "2017-03-21T18:40:28-07:00", 
    "noise": 1, 
    "system_time": "2017-03-22T00:30:36-07:00", 
    "direction": "Flat", 
    "sgv": 142, 
    "dateString": "2017-03-21T18:40:28-07:00", 
    "date": 1490146828000, 
    "unfiltered": 143488, 
    "filtered": 140000, 
    "device": "openaps://indy-ex2/cgm", 
    "rssi": 173, 
    "_id": "58d1d65c65110bbfc195de07", 
    "type": "sgv", 
    "glucose": 142
  }, 
  {
    "trend_arrow": "FLAT", 
    "display_time": "2017-03-21T18:35:32-07:00", 
    "noise": 1, 
    "system_time": "2017-03-22T01:34:33-07:00", 
    "direction": "Flat", 
    "sgv": 139, 
    "dateString": "2017-03-21T18:35:32-07:00", 
    "date": 1490146532000, 
    "unfiltered": 140800, 
    "filtered": 137856, 
    "device": "openaps://indy-e1/cgm", 
    "rssi": 186, 
    "_id": "58d1d5ad65110bbfc195de05", 
    "type": "sgv", 
    "glucose": 139
  }, 
  {
    "trend_arrow": "FLAT", 
    "display_time": "2017-03-21T18:35:28-07:00", 
    "noise": 1, 
    "system_time": "2017-03-22T00:25:36-07:00", 
    "direction": "Flat", 
    "sgv": 139, 
    "dateString": "2017-03-21T18:35:28-07:00", 
    "date": 1490146528000, 
    "unfiltered": 140800, 
    "filtered": 137856, 
    "device": "openaps://indy-ex2/cgm", 
    "rssi": 185, 
    "_id": "58d1d59365110bbfc195de04", 
    "type": "sgv", 
    "glucose": 139
  }, 
  {
    "trend_arrow": "FLAT", 
    "display_time": "2017-03-21T18:30:32-07:00", 
    "noise": 1, 
    "system_time": "2017-03-22T01:29:33-07:00", 
    "direction": "Flat", 
    "sgv": 136, 
    "dateString": "2017-03-21T18:30:32-07:00", 
    "date": 1490146232000, 
    "unfiltered": 138816, 
    "filtered": 135648, 
    "device": "openaps://indy-e1/cgm", 
    "rssi": 189, 
    "_id": "58d1d40365110bbfc195de01", 
    "type": "sgv", 
    "glucose": 136
  }, 
  {
    "trend_arrow": "FLAT", 
    "display_time": "2017-03-21T18:30:28-07:00", 
    "noise": 1, 
    "system_time": "2017-03-22T00:20:36-07:00", 
    "direction": "Flat", 
    "sgv": 136, 
    "dateString": "2017-03-21T18:30:28-07:00", 
    "date": 1490146228000, 
    "unfiltered": 138816, 
    "filtered": 135648, 
    "device": "openaps://indy-ex2/cgm", 
    "rssi": 183, 
    "_id": "58d1d40a65110bbfc195de03", 
    "type": "sgv", 
    "glucose": 136
  }, 
  {
    "trend_arrow": "FLAT", 
    "display_time": "2017-03-21T18:25:32-07:00", 
    "noise": 1, 
    "system_time": "2017-03-22T01:24:33-07:00", 
    "direction": "Flat", 
    "sgv": 134, 
    "dateString": "2017-03-21T18:25:32-07:00", 
    "date": 1490145932000, 
    "unfiltered": 137344, 
    "filtered": 133504, 
    "device": "openaps://indy-e1/cgm", 
    "rssi": 176, 
    "_id": "58d1d40365110bbfc195de02", 
    "type": "sgv", 
    "glucose": 134
  }, 
  {
    "trend_arrow": "FLAT", 
    "display_time": "2017-03-21T18:25:28-07:00", 
    "noise": 1, 
    "system_time": "2017-03-22T00:15:36-07:00", 
    "direction": "Flat", 
    "sgv": 134, 
    "dateString": "2017-03-21T18:25:28-07:00", 
    "date": 1490145928000, 
    "unfiltered": 137344, 
    "filtered": 133504, 
    "device": "openaps://indy-ex2/cgm", 
    "rssi": 194, 
    "_id": "58d1d2f165110bbfc195de00", 
    "type": "sgv", 
    "glucose": 134
  }, 
  {
    "trend_arrow": "FLAT", 
    "display_time": "2017-03-21T18:20:32-07:00", 
    "noise": 1, 
    "system_time": "2017-03-22T01:19:33-07:00", 
    "direction": "Flat", 
    "sgv": 131, 
    "dateString": "2017-03-21T18:20:32-07:00", 
    "date": 1490145632000, 
    "unfiltered": 134880, 
    "filtered": 131520, 
    "device": "openaps://indy-e1/cgm", 
    "rssi": 189, 
    "_id": "58d1d19565110bbfc195ddfc", 
    "type": "sgv", 
    "glucose": 131
  }, 
  {
    "trend_arrow": "FLAT", 
    "display_time": "2017-03-21T18:20:28-07:00", 
    "noise": 1, 
    "system_time": "2017-03-22T00:10:36-07:00", 
    "direction": "Flat", 
    "sgv": 131, 
    "dateString": "2017-03-21T18:20:28-07:00", 
    "date": 1490145628000, 
    "unfiltered": 134880, 
    "filtered": 131520, 
    "device": "openaps://indy-ex2/cgm", 
    "rssi": 193, 
    "_id": "58d1d1d965110bbfc195ddfd", 
    "type": "sgv", 
    "glucose": 131
  }, 
  {
    "trend_arrow": "FLAT", 
    "display_time": "2017-03-21T18:15:32-07:00", 
    "noise": 1, 
    "system_time": "2017-03-22T01:14:33-07:00", 
    "direction": "Flat", 
    "sgv": 127, 
    "dateString": "2017-03-21T18:15:32-07:00", 
    "date": 1490145332000, 
    "unfiltered": 132064, 
    "filtered": 129504, 
    "device": "openaps://indy-e1/cgm", 
    "rssi": 186, 
    "_id": "58d1d0c365110bbfc195ddfb", 
    "type": "sgv", 
    "glucose": 127
  }, 
  {
    "trend_arrow": "FLAT", 
    "display_time": "2017-03-21T18:15:28-07:00", 
    "noise": 1, 
    "system_time": "2017-03-22T00:05:36-07:00", 
    "direction": "Flat", 
    "sgv": 127, 
    "dateString": "2017-03-21T18:15:28-07:00", 
    "date": 1490145328000, 
    "unfiltered": 132064, 
    "filtered": 129504, 
    "device": "openaps://indy-ex2/cgm", 
    "rssi": 184, 
    "_id": "58d1d08f65110bbfc195ddf9", 
    "type": "sgv", 
    "glucose": 127
  }, 
  {
    "trend_arrow": "FLAT", 
    "display_time": "2017-03-21T18:10:32-07:00", 
    "noise": 1, 
    "system_time": "2017-03-22T01:09:33-07:00", 
    "direction": "Flat", 
    "sgv": 125, 
    "dateString": "2017-03-21T18:10:32-07:00", 
    "date": 1490145032000, 
    "unfiltered": 130528, 
    "filtered": 127040, 
    "device": "openaps://indy-e1/cgm", 
    "rssi": 196, 
    "_id": "58d1d04465110bbfc195ddf8", 
    "type": "sgv", 
    "glucose": 125
  }, 
  {
    "trend_arrow": "FLAT", 
    "display_time": "2017-03-21T18:10:28-07:00", 
    "noise": 1, 
    "system_time": "2017-03-22T00:00:36-07:00", 
    "direction": "Flat", 
    "sgv": 125, 
    "dateString": "2017-03-21T18:10:28-07:00", 
    "date": 1490145028000, 
    "unfiltered": 130528, 
    "filtered": 127040, 
    "device": "openaps://indy-ex2/cgm", 
    "rssi": 175, 
    "_id": "58d1d08f65110bbfc195ddfa", 
    "type": "sgv", 
    "glucose": 125
  }, 
  {
    "trend_arrow": "FLAT", 
    "display_time": "2017-03-21T18:05:32-07:00", 
    "noise": 1, 
    "system_time": "2017-03-22T01:04:34-07:00", 
    "direction": "Flat", 
    "sgv": 122, 
    "dateString": "2017-03-21T18:05:32-07:00", 
    "date": 1490144732000, 
    "unfiltered": 128208, 
    "filtered": 124160, 
    "device": "openaps://indy-e1/cgm", 
    "rssi": 429, 
    "_id": "58d1cefb65110bbfc195ddf7", 
    "type": "sgv", 
    "glucose": 122
  }, 
  {
    "trend_arrow": "FLAT", 
    "display_time": "2017-03-21T18:05:28-07:00", 
    "noise": 1, 
    "system_time": "2017-03-21T23:55:36-07:00", 
    "direction": "Flat", 
    "sgv": 122, 
    "dateString": "2017-03-21T18:05:28-07:00", 
    "date": 1490144728000, 
    "unfiltered": 128208, 
    "filtered": 124160, 
    "device": "openaps://indy-ex2/cgm", 
    "rssi": 190, 
    "_id": "58d1ce9265110bbfc195ddf6", 
    "type": "sgv", 
    "glucose": 122
  }, 
  {
    "trend_arrow": "FLAT", 
    "display_time": "2017-03-21T18:00:32-07:00", 
    "noise": 1, 
    "system_time": "2017-03-22T00:59:33-07:00", 
    "direction": "Flat", 
    "sgv": 120, 
    "dateString": "2017-03-21T18:00:32-07:00", 
    "date": 1490144432000, 
    "unfiltered": 126384, 
    "filtered": 121392, 
    "device": "openaps://indy-e1/cgm", 
    "rssi": 182, 
    "_id": "58d1ccfe65110bbfc195ddf3", 
    "type": "sgv", 
    "glucose": 120
  }, 
  {
    "trend_arrow": "FLAT", 
    "display_time": "2017-03-21T18:00:28-07:00", 
    "noise": 1, 
    "system_time": "2017-03-21T23:50:36-07:00", 
    "direction": "Flat", 
    "sgv": 120, 
    "dateString": "2017-03-21T18:00:28-07:00", 
    "date": 1490144428000, 
    "unfiltered": 126384, 
    "filtered": 121392, 
    "device": "openaps://indy-ex2/cgm", 
    "rssi": 197, 
    "_id": "58d1cda565110bbfc195ddf4", 
    "type": "sgv", 
    "glucose": 120
  }, 
  {
    "trend_arrow": "FLAT", 
    "display_time": "2017-03-21T17:55:32-07:00", 
    "noise": 1, 
    "system_time": "2017-03-22T00:54:34-07:00", 
    "direction": "Flat", 
    "sgv": 116, 
    "dateString": "2017-03-21T17:55:32-07:00", 
    "date": 1490144132000, 
    "unfiltered": 123008, 
    "filtered": 119536, 
    "device": "openaps://indy-e1/cgm", 
    "rssi": 450, 
    "_id": "58d1cbeb65110bbfc195ddf0", 
    "type": "sgv", 
    "glucose": 116
  }, 
  {
    "trend_arrow": "FLAT", 
    "display_time": "2017-03-21T17:55:28-07:00", 
    "noise": 1, 
    "system_time": "2017-03-21T23:45:36-07:00", 
    "direction": "Flat", 
    "sgv": 116, 
    "dateString": "2017-03-21T17:55:28-07:00", 
    "date": 1490144128000, 
    "unfiltered": 123008, 
    "filtered": 119536, 
    "device": "openaps://indy-ex2/cgm", 
    "rssi": 183, 
    "_id": "58d1cbda65110bbfc195ddef", 
    "type": "sgv", 
    "glucose": 116
  }, 
  {
    "trend_arrow": "FLAT", 
    "display_time": "2017-03-21T17:50:32-07:00", 
    "noise": 1, 
    "system_time": "2017-03-22T00:49:33-07:00", 
    "direction": "Flat", 
    "sgv": 113, 
    "dateString": "2017-03-21T17:50:32-07:00", 
    "date": 1490143832000, 
    "unfiltered": 121008, 
    "filtered": 119136, 
    "device": "openaps://indy-e1/cgm", 
    "rssi": 193, 
    "_id": "58d1cae465110bbfc195ddee", 
    "type": "sgv", 
    "glucose": 113
  }, 
  {
    "trend_arrow": "FLAT", 
    "display_time": "2017-03-21T17:50:28-07:00", 
    "noise": 1, 
    "system_time": "2017-03-21T23:40:37-07:00", 
    "direction": "Flat", 
    "sgv": 113, 
    "dateString": "2017-03-21T17:50:28-07:00", 
    "date": 1490143828000, 
    "unfiltered": 121008, 
    "filtered": 119136, 
    "device": "openaps://indy-ex2/cgm", 
    "rssi": 440, 
    "_id": "58d1caa365110bbfc195dded", 
    "type": "sgv", 
    "glucose": 113
  }, 
  {
    "trend_arrow": "FLAT", 
    "display_time": "2017-03-21T17:45:32-07:00", 
    "noise": 1, 
    "system_time": "2017-03-22T00:44:34-07:00", 
    "direction": "Flat", 
    "sgv": 111, 
    "dateString": "2017-03-21T17:45:32-07:00", 
    "date": 1490143532000, 
    "unfiltered": 119056, 
    "filtered": 119888, 
    "device": "openaps://indy-e1/cgm", 
    "rssi": 183, 
    "_id": "58d1c9b965110bbfc195ddeb", 
    "type": "sgv", 
    "glucose": 111
  }, 
  {
    "trend_arrow": "FLAT", 
    "display_time": "2017-03-21T17:45:28-07:00", 
    "noise": 1, 
    "system_time": "2017-03-21T23:35:36-07:00", 
    "direction": "Flat", 
    "sgv": 111, 
    "dateString": "2017-03-21T17:45:28-07:00", 
    "date": 1490143528000, 
    "unfiltered": 119056, 
    "filtered": 119888, 
    "device": "openaps://indy-ex2/cgm", 
    "rssi": 192, 
    "_id": "58d1ca2165110bbfc195ddec", 
    "type": "sgv", 
    "glucose": 111
  }, 
  {
    "trend_arrow": "FLAT", 
    "display_time": "2017-03-21T17:40:32-07:00", 
    "noise": 1, 
    "system_time": "2017-03-22T00:39:33-07:00", 
    "direction": "Flat", 
    "sgv": 111, 
    "dateString": "2017-03-21T17:40:32-07:00", 
    "date": 1490143232000, 
    "unfiltered": 118944, 
    "filtered": 120448, 
    "device": "openaps://indy-e1/cgm", 
    "rssi": 177, 
    "_id": "58d1c8bf65110bbfc195dde8", 
    "type": "sgv", 
    "glucose": 111
  }, 
  {
    "trend_arrow": "FLAT", 
    "display_time": "2017-03-21T17:40:28-07:00", 
    "noise": 1, 
    "system_time": "2017-03-21T23:30:36-07:00", 
    "direction": "Flat", 
    "sgv": 111, 
    "dateString": "2017-03-21T17:40:28-07:00", 
    "date": 1490143228000, 
    "unfiltered": 118944, 
    "filtered": 120448, 
    "device": "openaps://indy-ex2/cgm", 
    "rssi": 193, 
    "_id": "58d1c88a65110bbfc195dde7", 
    "type": "sgv", 
    "glucose": 111
  }, 
  {
    "trend_arrow": "FLAT", 
    "display_time": "2017-03-21T17:35:32-07:00", 
    "noise": 1, 
    "system_time": "2017-03-22T00:34:34-07:00", 
    "direction": "Flat", 
    "sgv": 110, 
    "dateString": "2017-03-21T17:35:32-07:00", 
    "date": 1490142932000, 
    "unfiltered": 118640, 
    "filtered": 119168, 
    "device": "openaps://indy-e1/cgm", 
    "rssi": 440, 
    "_id": "58d1c76665110bbfc195dde5", 
    "type": "sgv", 
    "glucose": 110
  }, 
  {
    "trend_arrow": "FLAT", 
    "display_time": "2017-03-21T17:35:28-07:00", 
    "noise": 1, 
    "system_time": "2017-03-21T23:25:36-07:00", 
    "direction": "Flat", 
    "sgv": 110, 
    "dateString": "2017-03-21T17:35:28-07:00", 
    "date": 1490142928000, 
    "unfiltered": 118640, 
    "filtered": 119168, 
    "device": "openaps://indy-ex2/cgm", 
    "rssi": 198, 
    "_id": "58d1c72765110bbfc195dde4", 
    "type": "sgv", 
    "glucose": 110
  }, 
  {
    "trend_arrow": "FLAT", 
    "display_time": "2017-03-21T17:30:32-07:00", 
    "noise": 1, 
    "system_time": "2017-03-22T00:29:33-07:00", 
    "direction": "Flat", 
    "sgv": 112, 
    "dateString": "2017-03-21T17:30:32-07:00", 
    "date": 1490142632000, 
    "unfiltered": 119712, 
    "filtered": 115520, 
    "device": "openaps://indy-e1/cgm", 
    "rssi": 194, 
    "_id": "58d1c68e65110bbfc195dde2", 
    "type": "sgv", 
    "glucose": 112
  }, 
  {
    "trend_arrow": "FLAT", 
    "display_time": "2017-03-21T17:30:28-07:00", 
    "noise": 1, 
    "system_time": "2017-03-21T23:20:36-07:00", 
    "direction": "Flat", 
    "sgv": 112, 
    "dateString": "2017-03-21T17:30:28-07:00", 
    "date": 1490142628000, 
    "unfiltered": 119712, 
    "filtered": 115520, 
    "device": "openaps://indy-ex2/cgm", 
    "rssi": 209, 
    "_id": "58d1c62165110bbfc195dde1", 
    "type": "sgv", 
    "glucose": 112
  }, 
  {
    "trend_arrow": "45_UP", 
    "display_time": "2017-03-21T17:25:34-07:00", 
    "noise": 1, 
    "system_time": "2017-03-22T00:24:35-07:00", 
    "direction": "FortyFiveUp", 
    "sgv": 111, 
    "dateString": "2017-03-21T17:25:34-07:00", 
    "date": 1490142334000, 
    "unfiltered": 118816, 
    "filtered": 111024, 
    "device": "openaps://indy-e1/cgm", 
    "rssi": 194, 
    "_id": "58d1c4ba65110bbfc195ddda", 
    "type": "sgv", 
    "glucose": 111
  }, 
  {
    "trend_arrow": "45_UP", 
    "display_time": "2017-03-21T17:25:33-07:00", 
    "noise": 1, 
    "system_time": "2017-03-22T00:24:35-07:00", 
    "direction": "FortyFiveUp", 
    "sgv": 113, 
    "dateString": "2017-03-21T17:25:33-07:00", 
    "device": "openaps://indy-e1/cgm", 
    "unfiltered": 115968, 
    "rssi": 173, 
    "date": 1490142333000, 
    "filtered": 107888, 
    "_id": "58d1c4ba65110bbfc195dddb", 
    "type": "sgv", 
    "glucose": 113
  }, 
  {
    "trend_arrow": "45_UP", 
    "display_time": "2017-03-21T17:25:29-07:00", 
    "noise": 1, 
    "system_time": "2017-03-21T23:15:38-07:00", 
    "direction": "FortyFiveUp", 
    "sgv": 113, 
    "dateString": "2017-03-21T17:25:29-07:00", 
    "date": 1490142329000, 
    "unfiltered": 115968, 
    "filtered": 107888, 
    "device": "openaps://indy-ex2/cgm", 
    "rssi": 184, 
    "_id": "58d1c59c65110bbfc195dddf", 
    "type": "sgv", 
    "glucose": 113
  }, 
  {
    "trend_arrow": "45_UP", 
    "display_time": "2017-03-21T17:25:29-07:00", 
    "noise": 1, 
    "system_time": "2017-03-21T23:15:38-07:00", 
    "direction": "FortyFiveUp", 
    "sgv": 111, 
    "dateString": "2017-03-21T17:25:29-07:00", 
    "date": 1490142329000, 
    "unfiltered": 118816, 
    "filtered": 111024, 
    "device": "openaps://indy-ex2/cgm", 
    "rssi": 180, 
    "_id": "58d1c59c65110bbfc195ddde", 
    "type": "sgv", 
    "glucose": 111
  }, 
  {
    "trend_arrow": "FLAT", 
    "display_time": "2017-03-21T17:20:32-07:00", 
    "noise": 1, 
    "system_time": "2017-03-22T00:19:33-07:00", 
    "direction": "Flat", 
    "sgv": 109, 
    "dateString": "2017-03-21T17:20:32-07:00", 
    "device": "openaps://indy-e1/cgm", 
    "unfiltered": 109568, 
    "rssi": 168, 
    "date": 1490142032000, 
    "filtered": 106240, 
    "_id": "58d1c4e065110bbfc195dddd", 
    "type": "sgv", 
    "glucose": 109
  }, 
  {
    "trend_arrow": "FLAT", 
    "display_time": "2017-03-21T17:20:32-07:00", 
    "noise": 1, 
    "system_time": "2017-03-22T00:19:33-07:00", 
    "direction": "Flat", 
    "sgv": 109, 
    "dateString": "2017-03-21T17:20:32-07:00", 
    "date": 1490142032000, 
    "unfiltered": 115968, 
    "filtered": 107888, 
    "device": "openaps://indy-e1/cgm", 
    "rssi": 173, 
    "_id": "58d1c3dc65110bbfc195ddd7", 
    "type": "sgv", 
    "glucose": 109
  }, 
  {
    "trend_arrow": "FLAT", 
    "display_time": "2017-03-21T17:15:32-07:00", 
    "noise": 1, 
    "system_time": "2017-03-22T00:14:34-07:00", 
    "direction": "Flat", 
    "sgv": 98, 
    "dateString": "2017-03-21T17:15:32-07:00", 
    "date": 1490141732000, 
    "unfiltered": 109568, 
    "filtered": 106240, 
    "device": "openaps://indy-e1/cgm", 
    "rssi": 168, 
    "_id": "58d1c32865110bbfc195ddd6", 
    "type": "sgv", 
    "glucose": 98
  }, 
  {
    "trend_arrow": "FLAT", 
    "display_time": "2017-03-21T17:15:28-07:00", 
    "noise": 1, 
    "system_time": "2017-03-21T23:05:36-07:00", 
    "direction": "Flat", 
    "sgv": 98, 
    "dateString": "2017-03-21T17:15:28-07:00", 
    "date": 1490141728000, 
    "unfiltered": 109568, 
    "filtered": 106240, 
    "device": "openaps://indy-ex2/cgm", 
    "rssi": 197, 
    "_id": "58d1c27d65110bbfc195ddd5", 
    "type": "sgv", 
    "glucose": 98
  }, 
  {
    "trend_arrow": "FLAT", 
    "display_time": "2017-03-21T17:10:32-07:00", 
    "noise": 1, 
    "system_time": "2017-03-22T00:09:34-07:00", 
    "direction": "Flat", 
    "sgv": 90, 
    "dateString": "2017-03-21T17:10:32-07:00", 
    "date": 1490141432000, 
    "unfiltered": 103408, 
    "filtered": 104624, 
    "device": "openaps://indy-e1/cgm", 
    "rssi": 180, 
    "_id": "58d1c18465110bbfc195ddd3", 
    "type": "sgv", 
    "glucose": 90
  }, 
  {
    "trend_arrow": "FLAT", 
    "display_time": "2017-03-21T17:10:28-07:00", 
    "noise": 1, 
    "system_time": "2017-03-21T23:00:36-07:00", 
    "direction": "Flat", 
    "sgv": 90, 
    "dateString": "2017-03-21T17:10:28-07:00", 
    "date": 1490141428000, 
    "unfiltered": 103408, 
    "filtered": 104624, 
    "device": "openaps://indy-ex2/cgm", 
    "rssi": 166, 
    "_id": "58d1c14a65110bbfc195ddd2", 
    "type": "sgv", 
    "glucose": 90
  }, 
  {
    "trend_arrow": "FLAT", 
    "display_time": "2017-03-21T17:05:32-07:00", 
    "noise": 1, 
    "system_time": "2017-03-22T00:04:34-07:00", 
    "direction": "Flat", 
    "sgv": 94, 
    "dateString": "2017-03-21T17:05:32-07:00", 
    "date": 1490141132000, 
    "unfiltered": 106048, 
    "filtered": 101600, 
    "device": "openaps://indy-e1/cgm", 
    "rssi": 180, 
    "_id": "58d1c02065110bbfc195ddd0", 
    "type": "sgv", 
    "glucose": 94
  }, 
  {
    "trend_arrow": "45_UP", 
    "display_time": "2017-03-21T17:05:28-07:00", 
    "noise": 1, 
    "system_time": "2017-03-21T22:55:36-07:00", 
    "direction": "FortyFiveUp", 
    "sgv": 94, 
    "dateString": "2017-03-21T17:05:28-07:00", 
    "date": 1490141128000, 
    "unfiltered": 106048, 
    "filtered": 101600, 
    "device": "openaps://indy-ex2/cgm", 
    "rssi": 166, 
    "_id": "58d1c0d065110bbfc195ddd1", 
    "type": "sgv", 
    "glucose": 94
  }, 
  {
    "trend_arrow": "45_UP", 
    "display_time": "2017-03-21T17:00:32-07:00", 
    "noise": 1, 
    "system_time": "2017-03-21T23:59:34-07:00", 
    "direction": "FortyFiveUp", 
    "sgv": 92, 
    "dateString": "2017-03-21T17:00:32-07:00", 
    "date": 1490140832000, 
    "unfiltered": 104384, 
    "filtered": 97232, 
    "device": "openaps://indy-e1/cgm", 
    "rssi": 187, 
    "_id": "58d1beea65110bbfc195ddce", 
    "type": "sgv", 
    "glucose": 92
  }, 
  {
    "trend_arrow": "45_UP", 
    "display_time": "2017-03-21T16:55:33-07:00", 
    "noise": 1, 
    "system_time": "2017-03-21T23:54:34-07:00", 
    "direction": "FortyFiveUp", 
    "sgv": 86, 
    "dateString": "2017-03-21T16:55:33-07:00", 
    "date": 1490140533000, 
    "unfiltered": 99824, 
    "filtered": 92752, 
    "device": "openaps://indy-e1/cgm", 
    "rssi": 433, 
    "_id": "58d1bdfd65110bbfc195ddcd", 
    "type": "sgv", 
    "glucose": 86
  }, 
  {
    "trend_arrow": "45_UP", 
    "display_time": "2017-03-21T16:55:28-07:00", 
    "noise": 1, 
    "system_time": "2017-03-21T22:45:37-07:00", 
    "direction": "FortyFiveUp", 
    "sgv": 86, 
    "dateString": "2017-03-21T16:55:28-07:00", 
    "date": 1490140528000, 
    "unfiltered": 99824, 
    "filtered": 92752, 
    "device": "openaps://indy-ex2/cgm", 
    "rssi": 441, 
    "_id": "58d1bdab65110bbfc195ddcc", 
    "type": "sgv", 
    "glucose": 86
  }, 
  {
    "trend_arrow": "FLAT", 
    "display_time": "2017-03-21T16:50:32-07:00", 
    "noise": 1, 
    "system_time": "2017-03-21T23:49:34-07:00", 
    "direction": "Flat", 
    "sgv": 80, 
    "dateString": "2017-03-21T16:50:32-07:00", 
    "date": 1490140232000, 
    "unfiltered": 95424, 
    "filtered": 88928, 
    "device": "openaps://indy-e1/cgm", 
    "rssi": 188, 
    "_id": "58d1bd0c65110bbfc195ddcb", 
    "type": "sgv", 
    "glucose": 80
  }, 
  {
    "trend_arrow": "FLAT", 
    "display_time": "2017-03-21T16:50:28-07:00", 
    "noise": 1, 
    "system_time": "2017-03-21T22:40:36-07:00", 
    "direction": "Flat", 
    "sgv": 80, 
    "dateString": "2017-03-21T16:50:28-07:00", 
    "date": 1490140228000, 
    "unfiltered": 95424, 
    "filtered": 88928, 
    "device": "openaps://indy-ex2/cgm", 
    "rssi": 166, 
    "_id": "58d1bcbb65110bbfc195ddc9", 
    "type": "sgv", 
    "glucose": 80
  }, 
  {
    "trend_arrow": "FLAT", 
    "display_time": "2017-03-21T16:45:32-07:00", 
    "noise": 1, 
    "system_time": "2017-03-21T23:44:34-07:00", 
    "direction": "Flat", 
    "sgv": 75, 
    "dateString": "2017-03-21T16:45:32-07:00", 
    "date": 1490139932000, 
    "unfiltered": 91456, 
    "filtered": 85760, 
    "device": "openaps://indy-e1/cgm", 
    "rssi": 186, 
    "_id": "58d1bb5265110bbfc195ddc7", 
    "type": "sgv", 
    "glucose": 75
  }, 
  {
    "trend_arrow": "NOT_COMPUTABLE", 
    "display_time": "2017-03-21T16:45:28-07:00", 
    "noise": 1, 
    "system_time": "2017-03-21T22:35:36-07:00", 
    "direction": "NOT COMPUTABLE", 
    "sgv": 75, 
    "dateString": "2017-03-21T16:45:28-07:00", 
    "date": 1490139928000, 
    "unfiltered": 91456, 
    "filtered": 85760, 
    "device": "openaps://indy-ex2/cgm", 
    "rssi": 172, 
    "_id": "58d1bb6965110bbfc195ddc8", 
    "type": "sgv", 
    "glucose": 75
  }, 
  {
    "trend_arrow": "FLAT", 
    "display_time": "2017-03-21T16:40:32-07:00", 
    "noise": 1, 
    "system_time": "2017-03-21T23:39:34-07:00", 
    "direction": "Flat", 
    "sgv": 68, 
    "dateString": "2017-03-21T16:40:32-07:00", 
    "date": 1490139632000, 
    "unfiltered": 86000, 
    "filtered": 83200, 
    "device": "openaps://indy-e1/cgm", 
    "rssi": 190, 
    "_id": "58d1ba2665110bbfc195ddc5", 
    "type": "sgv", 
    "glucose": 68
  }, 
  {
    "trend_arrow": "NOT_COMPUTABLE", 
    "display_time": "2017-03-21T16:40:28-07:00", 
    "noise": 1, 
    "system_time": "2017-03-21T22:30:36-07:00", 
    "direction": "NOT COMPUTABLE", 
    "sgv": 68, 
    "dateString": "2017-03-21T16:40:28-07:00", 
    "date": 1490139628000, 
    "unfiltered": 86000, 
    "filtered": 83200, 
    "device": "openaps://indy-ex2/cgm", 
    "rssi": 169, 
    "_id": "58d1ba3165110bbfc195ddc6", 
    "type": "sgv", 
    "glucose": 68
  }, 
  {
    "trend_arrow": "FLAT", 
    "display_time": "2017-03-21T16:35:32-07:00", 
    "noise": 1, 
    "system_time": "2017-03-21T23:34:34-07:00", 
    "direction": "Flat", 
    "sgv": 67, 
    "dateString": "2017-03-21T16:35:32-07:00", 
    "date": 1490139332000, 
    "unfiltered": 85120, 
    "filtered": 81616, 
    "device": "openaps://indy-e1/cgm", 
    "rssi": 184, 
    "_id": "58d1b95e65110bbfc195ddc3", 
    "type": "sgv", 
    "glucose": 67
  }, 
  {
    "trend_arrow": "FLAT", 
    "display_time": "2017-03-21T16:30:32-07:00", 
    "noise": 1, 
    "system_time": "2017-03-21T23:29:34-07:00", 
    "direction": "Flat", 
    "sgv": 65, 
    "dateString": "2017-03-21T16:30:32-07:00", 
    "date": 1490139032000, 
    "unfiltered": 83728, 
    "filtered": 81280, 
    "device": "openaps://indy-e1/cgm", 
    "rssi": 193, 
    "_id": "58d1b7e665110bbfc195ddc0", 
    "type": "sgv", 
    "glucose": 65
  }, 
  {
    "trend_arrow": "NOT_COMPUTABLE", 
    "display_time": "2017-03-21T16:30:28-07:00", 
    "noise": 1, 
    "system_time": "2017-03-21T22:20:37-07:00", 
    "direction": "NOT COMPUTABLE", 
    "sgv": 65, 
    "dateString": "2017-03-21T16:30:28-07:00", 
    "date": 1490139028000, 
    "unfiltered": 83728, 
    "filtered": 81280, 
    "device": "openaps://indy-ex2/cgm", 
    "rssi": 425, 
    "_id": "58d1b83965110bbfc195ddc1", 
    "type": "sgv", 
    "glucose": 65
  }, 
  {
    "trend_arrow": "FLAT", 
    "display_time": "2017-03-21T16:25:32-07:00", 
    "noise": 1, 
    "system_time": "2017-03-21T23:24:34-07:00", 
    "direction": "Flat", 
    "sgv": 61, 
    "dateString": "2017-03-21T16:25:32-07:00", 
    "date": 1490138732000, 
    "unfiltered": 80128, 
    "filtered": 82192, 
    "device": "openaps://indy-e1/cgm", 
    "rssi": 179, 
    "_id": "58d1b70865110bbfc195ddbd", 
    "type": "sgv", 
    "glucose": 61
  }, 
  {
    "trend_arrow": "NOT_COMPUTABLE", 
    "display_time": "2017-03-21T16:25:29-07:00", 
    "noise": 1, 
    "system_time": "2017-03-21T22:15:37-07:00", 
    "direction": "NOT COMPUTABLE", 
    "sgv": 61, 
    "dateString": "2017-03-21T16:25:29-07:00", 
    "date": 1490138729000, 
    "unfiltered": 80128, 
    "filtered": 82192, 
    "device": "openaps://indy-ex2/cgm", 
    "rssi": 686, 
    "_id": "58d1b72c65110bbfc195ddbe", 
    "type": "sgv", 
    "glucose": 61
  }, 
  {
    "trend_arrow": "FLAT", 
    "display_time": "2017-03-21T16:20:32-07:00", 
    "noise": 1, 
    "system_time": "2017-03-21T23:19:34-07:00", 
    "direction": "Flat", 
    "sgv": 62, 
    "dateString": "2017-03-21T16:20:32-07:00", 
    "date": 1490138432000, 
    "unfiltered": 81056, 
    "filtered": 83856, 
    "device": "openaps://indy-e1/cgm", 
    "rssi": 176, 
    "_id": "58d1b59665110bbfc195ddbc", 
    "type": "sgv", 
    "glucose": 62
  }, 
  {
    "trend_arrow": "FLAT", 
    "display_time": "2017-03-21T16:15:32-07:00", 
    "noise": 1, 
    "system_time": "2017-03-21T23:14:34-07:00", 
    "direction": "Flat", 
    "sgv": 65, 
    "dateString": "2017-03-21T16:15:32-07:00", 
    "date": 1490138132000, 
    "unfiltered": 83360, 
    "filtered": 86016, 
    "device": "openaps://indy-e1/cgm", 
    "rssi": 174, 
    "_id": "58d1b4b065110bbfc195ddba", 
    "type": "sgv", 
    "glucose": 65
  }, 
  {
    "trend_arrow": "FLAT", 
    "display_time": "2017-03-21T16:10:32-07:00", 
    "noise": 1, 
    "system_time": "2017-03-21T23:09:34-07:00", 
    "direction": "Flat", 
    "sgv": 67, 
    "dateString": "2017-03-21T16:10:32-07:00", 
    "date": 1490137832000, 
    "unfiltered": 85376, 
    "filtered": 88624, 
    "device": "openaps://indy-e1/cgm", 
    "rssi": 186, 
    "_id": "58d1b33765110bbfc195ddb8", 
    "type": "sgv", 
    "glucose": 67
  }, 
  {
    "trend_arrow": "FLAT", 
    "display_time": "2017-03-21T16:05:32-07:00", 
    "noise": 1, 
    "system_time": "2017-03-21T23:04:34-07:00", 
    "direction": "Flat", 
    "sgv": 69, 
    "dateString": "2017-03-21T16:05:32-07:00", 
    "date": 1490137532000, 
    "unfiltered": 86224, 
    "filtered": 91360, 
    "device": "openaps://indy-e1/cgm", 
    "rssi": 187, 
    "_id": "58d1b20865110bbfc195ddb7", 
    "type": "sgv", 
    "glucose": 69
  }, 
  {
    "trend_arrow": "FLAT", 
    "display_time": "2017-03-21T16:00:32-07:00", 
    "noise": 1, 
    "system_time": "2017-03-21T22:59:34-07:00", 
    "direction": "Flat", 
    "sgv": 74, 
    "dateString": "2017-03-21T16:00:32-07:00", 
    "date": 1490137232000, 
    "unfiltered": 90192, 
    "filtered": 93248, 
    "device": "openaps://indy-e1/cgm", 
    "rssi": 190, 
    "_id": "58d1b11f65110bbfc195ddb5", 
    "type": "sgv", 
    "glucose": 74
  }, 
  {
    "trend_arrow": "FLAT", 
    "display_time": "2017-03-21T15:55:32-07:00", 
    "noise": 1, 
    "system_time": "2017-03-21T22:54:34-07:00", 
    "direction": "Flat", 
    "sgv": 75, 
    "dateString": "2017-03-21T15:55:32-07:00", 
    "date": 1490136932000, 
    "unfiltered": 91424, 
    "filtered": 93248, 
    "device": "openaps://indy-e1/cgm", 
    "rssi": 196, 
    "_id": "58d1af9965110bbfc195ddb3", 
    "type": "sgv", 
    "glucose": 75
  }, 
  {
    "trend_arrow": "FLAT", 
    "display_time": "2017-03-21T15:50:32-07:00", 
    "noise": 1, 
    "system_time": "2017-03-21T22:49:34-07:00", 
    "direction": "Flat", 
    "sgv": 77, 
    "dateString": "2017-03-21T15:50:32-07:00", 
    "date": 1490136632000, 
    "unfiltered": 93008, 
    "filtered": 91120, 
    "device": "openaps://indy-e1/cgm", 
    "rssi": 194, 
    "_id": "58d1aebf65110bbfc195ddb2", 
    "type": "sgv", 
    "glucose": 77
  }, 
  {
    "trend_arrow": "FLAT", 
    "display_time": "2017-03-21T15:45:32-07:00", 
    "noise": 1, 
    "system_time": "2017-03-21T22:44:34-07:00", 
    "direction": "Flat", 
    "sgv": 78, 
    "dateString": "2017-03-21T15:45:32-07:00", 
    "date": 1490136332000, 
    "unfiltered": 93328, 
    "filtered": 87808, 
    "device": "openaps://indy-e1/cgm", 
    "rssi": 169, 
    "_id": "58d1ad4765110bbfc195ddb1", 
    "type": "sgv", 
    "glucose": 78
  }, 
  {
    "trend_arrow": "FLAT", 
    "display_time": "2017-03-21T15:40:32-07:00", 
    "noise": 1, 
    "system_time": "2017-03-21T22:39:34-07:00", 
    "direction": "Flat", 
    "sgv": 75, 
    "dateString": "2017-03-21T15:40:32-07:00", 
    "date": 1490136032000, 
    "unfiltered": 90992, 
    "filtered": 85120, 
    "device": "openaps://indy-e1/cgm", 
    "rssi": 180, 
    "_id": "58d1ac1665110bbfc195ddaf", 
    "type": "sgv", 
    "glucose": 75
  }, 
  {
    "trend_arrow": "FLAT", 
    "display_time": "2017-03-21T15:35:33-07:00", 
    "noise": 1, 
    "system_time": "2017-03-21T22:34:34-07:00", 
    "direction": "Flat", 
    "sgv": 70, 
    "dateString": "2017-03-21T15:35:33-07:00", 
    "device": "openaps://indy-e1/cgm", 
    "unfiltered": 87296, 
    "rssi": 449, 
    "date": 1490135733000, 
    "filtered": 84128, 
    "_id": "58d1ab2865110bbfc195ddad", 
    "type": "sgv", 
    "glucose": 70
  }, 
  {
    "trend_arrow": "FLAT", 
    "display_time": "2017-03-21T15:30:32-07:00", 
    "noise": 1, 
    "system_time": "2017-03-21T22:29:34-07:00", 
    "direction": "Flat", 
    "sgv": 65, 
    "dateString": "2017-03-21T15:30:32-07:00", 
    "date": 1490135432000, 
    "unfiltered": 83200, 
    "filtered": 84656, 
    "device": "openaps://indy-e1/cgm", 
    "rssi": 184, 
    "_id": "58d1aa2965110bbfc195ddac", 
    "type": "sgv", 
    "glucose": 65
  }, 
  {
    "trend_arrow": "FLAT", 
    "display_time": "2017-03-21T15:25:32-07:00", 
    "noise": 1, 
    "system_time": "2017-03-21T22:24:34-07:00", 
    "direction": "Flat", 
    "sgv": 65, 
    "dateString": "2017-03-21T15:25:32-07:00", 
    "date": 1490135132000, 
    "unfiltered": 83776, 
    "filtered": 86112, 
    "device": "openaps://indy-e1/cgm", 
    "rssi": 204, 
    "_id": "58d1a8ed65110bbfc195ddab", 
    "type": "sgv", 
    "glucose": 65
  }, 
  {
    "trend_arrow": "FLAT", 
    "display_time": "2017-03-21T15:20:32-07:00", 
    "noise": 1, 
    "system_time": "2017-03-21T22:19:34-07:00", 
    "direction": "Flat", 
    "sgv": 68, 
    "dateString": "2017-03-21T15:20:32-07:00", 
    "date": 1490134832000, 
    "unfiltered": 85824, 
    "filtered": 88256, 
    "device": "openaps://indy-e1/cgm", 
    "rssi": 191, 
    "_id": "58d1a7eb65110bbfc195dda9", 
    "type": "sgv", 
    "glucose": 68
  }, 
  {
    "trend_arrow": "FLAT", 
    "display_time": "2017-03-21T15:15:32-07:00", 
    "noise": 1, 
    "system_time": "2017-03-21T22:14:34-07:00", 
    "direction": "Flat", 
    "sgv": 70, 
    "dateString": "2017-03-21T15:15:32-07:00", 
    "date": 1490134532000, 
    "unfiltered": 87248, 
    "filtered": 91296, 
    "device": "openaps://indy-e1/cgm", 
    "rssi": 203, 
    "_id": "58d1a6dd65110bbfc195dda8", 
    "type": "sgv", 
    "glucose": 70
  }, 
  {
    "trend_arrow": "45_DOWN", 
    "display_time": "2017-03-21T15:10:32-07:00", 
    "noise": 1, 
    "system_time": "2017-03-21T22:09:34-07:00", 
    "direction": "FortyFiveDown", 
    "sgv": 72, 
    "dateString": "2017-03-21T15:10:32-07:00", 
    "date": 1490134232000, 
    "unfiltered": 89040, 
    "filtered": 95376, 
    "device": "openaps://indy-e1/cgm", 
    "rssi": 188, 
    "_id": "58d1a55965110bbfc195dda6", 
    "type": "sgv", 
    "glucose": 72
  }, 
  {
    "trend_arrow": "45_DOWN", 
    "display_time": "2017-03-21T15:05:32-07:00", 
    "noise": 1, 
    "system_time": "2017-03-21T22:04:34-07:00", 
    "direction": "FortyFiveDown", 
    "sgv": 78, 
    "dateString": "2017-03-21T15:05:32-07:00", 
    "date": 1490133932000, 
    "unfiltered": 93408, 
    "filtered": 100672, 
    "device": "openaps://indy-e1/cgm", 
    "rssi": 188, 
    "_id": "58d1a41765110bbfc195dda5", 
    "type": "sgv", 
    "glucose": 78
  }, 
  {
    "trend_arrow": "SINGLE_DOWN", 
    "display_time": "2017-03-21T15:00:32-07:00", 
    "noise": 1, 
    "system_time": "2017-03-21T21:59:34-07:00", 
    "direction": "SingleDown", 
    "sgv": 83, 
    "dateString": "2017-03-21T15:00:32-07:00", 
    "date": 1490133632000, 
    "unfiltered": 97920, 
    "filtered": 107648, 
    "device": "openaps://indy-e1/cgm", 
    "rssi": 181, 
    "_id": "58d1a30c65110bbfc195dda3", 
    "type": "sgv", 
    "glucose": 83
  }, 
  {
    "trend_arrow": "SINGLE_DOWN", 
    "display_time": "2017-03-21T14:55:32-07:00", 
    "noise": 1, 
    "system_time": "2017-03-21T21:54:34-07:00", 
    "direction": "SingleDown", 
    "sgv": 91, 
    "dateString": "2017-03-21T14:55:32-07:00", 
    "date": 1490133332000, 
    "unfiltered": 104032, 
    "filtered": 117056, 
    "device": "openaps://indy-e1/cgm", 
    "rssi": 192, 
    "_id": "58d1a1a365110bbfc195dda1", 
    "type": "sgv", 
    "glucose": 91
  }, 
  {
    "trend_arrow": "DOUBLE_DOWN", 
    "display_time": "2017-03-21T14:50:32-07:00", 
    "noise": 1, 
    "system_time": "2017-03-21T21:49:34-07:00", 
    "direction": "DoubleDown", 
    "sgv": 102, 
    "dateString": "2017-03-21T14:50:32-07:00", 
    "date": 1490133032000, 
    "unfiltered": 112240, 
    "filtered": 129200, 
    "device": "openaps://indy-e1/cgm", 
    "rssi": 181, 
    "_id": "58d1a10c65110bbfc195dda0", 
    "type": "sgv", 
    "glucose": 102
  }, 
  {
    "trend_arrow": "DOUBLE_DOWN", 
    "display_time": "2017-03-21T14:45:32-07:00", 
    "noise": 1, 
    "system_time": "2017-03-21T21:44:34-07:00", 
    "direction": "DoubleDown", 
    "sgv": 115, 
    "dateString": "2017-03-21T14:45:32-07:00", 
    "date": 1490132732000, 
    "unfiltered": 122672, 
    "filtered": 143136, 
    "device": "openaps://indy-e1/cgm", 
    "rssi": 176, 
    "_id": "58d19ff765110bbfc195dd9f", 
    "type": "sgv", 
    "glucose": 115
  }, 
  {
    "trend_arrow": "DOUBLE_DOWN", 
    "display_time": "2017-03-21T14:40:33-07:00", 
    "noise": 1, 
    "system_time": "2017-03-21T21:39:34-07:00", 
    "direction": "DoubleDown", 
    "sgv": 129, 
    "dateString": "2017-03-21T14:40:33-07:00", 
    "date": 1490132433000, 
    "unfiltered": 133536, 
    "filtered": 156704, 
    "device": "openaps://indy-e1/cgm", 
    "rssi": 447, 
    "_id": "58d19e8f65110bbfc195dd9d", 
    "type": "sgv", 
    "glucose": 129
  }, 
  {
    "trend_arrow": "SINGLE_DOWN", 
    "display_time": "2017-03-21T14:35:33-07:00", 
    "noise": 1, 
    "system_time": "2017-03-21T21:34:34-07:00", 
    "direction": "SingleDown", 
    "sgv": 148, 
    "dateString": "2017-03-21T14:35:33-07:00", 
    "date": 1490132133000, 
    "unfiltered": 148224, 
    "filtered": 167744, 
    "device": "openaps://indy-e1/cgm", 
    "rssi": 433, 
    "_id": "58d19cf965110bbfc195dd9c", 
    "type": "sgv", 
    "glucose": 148
  }, 
  {
    "trend_arrow": "45_DOWN", 
    "display_time": "2017-03-21T14:30:33-07:00", 
    "noise": 1, 
    "system_time": "2017-03-21T21:29:34-07:00", 
    "direction": "FortyFiveDown", 
    "sgv": 167, 
    "dateString": "2017-03-21T14:30:33-07:00", 
    "date": 1490131833000, 
    "unfiltered": 163232, 
    "filtered": 174816, 
    "device": "openaps://indy-e1/cgm", 
    "rssi": 440, 
    "_id": "58d19c3f65110bbfc195dd9a", 
    "type": "sgv", 
    "glucose": 167
  }, 
  {
    "trend_arrow": "FLAT", 
    "display_time": "2017-03-21T14:25:32-07:00", 
    "noise": 1, 
    "system_time": "2017-03-21T21:24:34-07:00", 
    "direction": "Flat", 
    "sgv": 176, 
    "dateString": "2017-03-21T14:25:32-07:00", 
    "device": "openaps://indy-e1/cgm", 
    "unfiltered": 170688, 
    "rssi": 181, 
    "date": 1490131532000, 
    "filtered": 177824, 
    "_id": "58d19af965110bbfc195dd98", 
    "type": "sgv", 
    "glucose": 176
  }, 
  {
    "trend_arrow": "FLAT", 
    "display_time": "2017-03-21T14:20:32-07:00", 
    "noise": 1, 
    "system_time": "2017-03-21T21:19:34-07:00", 
    "direction": "Flat", 
    "sgv": 185, 
    "dateString": "2017-03-21T14:20:32-07:00", 
    "date": 1490131232000, 
    "unfiltered": 177216, 
    "filtered": 177248, 
    "device": "openaps://indy-e1/cgm", 
    "rssi": 179, 
    "_id": "58d199f065110bbfc195dd96", 
    "type": "sgv", 
    "glucose": 185
  }, 
  {
    "trend_arrow": "FLAT", 
    "display_time": "2017-03-21T14:15:32-07:00", 
    "noise": 1, 
    "system_time": "2017-03-21T21:14:34-07:00", 
    "direction": "Flat", 
    "sgv": 186, 
    "dateString": "2017-03-21T14:15:32-07:00", 
    "date": 1490130932000, 
    "unfiltered": 178304, 
    "filtered": 174112, 
    "device": "openaps://indy-e1/cgm", 
    "rssi": 183, 
    "_id": "58d198cd65110bbfc195dd94", 
    "type": "sgv", 
    "glucose": 186
  }, 
  {
    "trend_arrow": "FLAT", 
    "display_time": "2017-03-21T14:10:32-07:00", 
    "noise": 1, 
    "system_time": "2017-03-21T21:09:34-07:00", 
    "direction": "Flat", 
    "sgv": 184, 
    "dateString": "2017-03-21T14:10:32-07:00", 
    "date": 1490130632000, 
    "unfiltered": 176928, 
    "filtered": 170208, 
    "device": "openaps://indy-e1/cgm", 
    "rssi": 185, 
    "_id": "58d1974865110bbfc195dd92", 
    "type": "sgv", 
    "glucose": 184
  }
]