{
  "device": "openaps://indy-ex2", 
  "pump": {
    "battery": {
      "status": "normal", 
      "voltage": 1.58
    }, 
    "status": {
      "status": "normal", 
      "timestamp": "2017-04-17T22:41:31.856Z", 
      "bolusing": false, 
      "suspended": false
    }, 
    "reservoir": 94.425, 
    "clock": "2017-04-17T15:41:25-07:00"
  }, 
  "uploader": {
    "battery": 87, 
    "batteryVoltage": 4054
  }, 
  "openaps": {
    "suggested": {
      "bg": 99, 
      "temp": "absolute", 
      "snoozeBG": 128, 
      "timestamp": "2017-04-17T22:45:00.069Z", 
      "reason": "COB: 25, Dev: 45, BGI: -5.2, ISF: 91, Target: 98; Eventual BG 253 >= 98, temp 1.05<1.3U/hr", 
      "rate": 1.3, 
      "COB": 25, 
      "eventualBG": 253, 
      "duration": 30, 
      "tick": "+3", 
      "IOB": 0.34
    }, 
    "iob": {
      "netbasalinsulin": 1.4, 
      "timestamp": "2017-04-17T22:41:25.000Z", 
      "activity": 0.0114, 
      "basaliob": 0.34, 
      "hightempinsulin": 1.7, 
      "bolussnooze": 0, 
      "iob": 0.34
    }, 
    "enacted": {
      "bg": 99, 
      "temp": "absolute", 
      "snoozeBG": 128, 
      "recieved": true, 
      "predBGs": {
        "COB": [
          99, 
          101, 
          104, 
          106, 
          109, 
          113, 
          116, 
          120, 
          124, 
          128, 
          133, 
          137, 
          142, 
          146, 
          151, 
          156, 
          160, 
          165, 
          169, 
          174, 
          178, 
          182, 
          187, 
          191, 
          195, 
          199, 
          202, 
          206, 
          210, 
          213, 
          217, 
          220, 
          223, 
          227, 
          230, 
          233, 
          236, 
          239, 
          242, 
          245, 
          247, 
          250, 
          253
        ], 
        "aCOB": [
          99, 
          104, 
          108, 
          113, 
          118, 
          124, 
          129, 
          135, 
          141, 
          147, 
          153, 
          159, 
          165, 
          171, 
          176, 
          182, 
          188, 
          193, 
          199, 
          204, 
          209, 
          214, 
          218, 
          223, 
          227, 
          231, 
          235, 
          239, 
          242, 
          246, 
          249, 
          252, 
          255, 
          257, 
          260, 
          262, 
          265, 
          267, 
          269, 
          270, 
          272, 
          273, 
          275
        ], 
        "IOB": [
          99, 
          101, 
          102, 
          103, 
          104, 
          105, 
          106, 
          106, 
          106, 
          106, 
          105, 
          104, 
          102, 
          101, 
          100, 
          99, 
          98, 
          97, 
          96, 
          95, 
          94, 
          93, 
          93, 
          92, 
          91, 
          91, 
          90, 
          90, 
          89, 
          89, 
          88, 
          87, 
          87, 
          87, 
          86
        ]
      }, 
      "rate": 1.05, 
      "reason": "COB: 25, Dev: 45, BGI: -5.2, ISF: 91, Target: 98; Eventual BG 253 >= 98, temp 1.05<1.3U/hr", 
      "COB": 25, 
      "eventualBG": 253, 
      "timestamp": "2017-04-17T22:45:33.320Z", 
      "duration": 25, 
      "tick": "+3", 
      "IOB": 0.34
    }
  }, 
  "mmtune": {
    "scanDetails": [
      [
        null, 
        0, 
        -59.8
      ]
    ], 
    "timestamp": "2017-04-17T22:45:41.480Z"
  }
}