{
  "device": "openaps://indy-ex2", 
  "pump": {
    "battery": {
      "status": "normal", 
      "voltage": 1.54
    }, 
    "status": {
      "status": "normal", 
      "timestamp": "2017-04-24T01:03:32.609Z", 
      "bolusing": false, 
      "suspended": false
    }, 
    "reservoir": 123.075, 
    "clock": "2017-04-23T18:02:20-07:00"
  }, 
  "uploader": {
    "battery": 55, 
    "batteryVoltage": 3732
  }, 
  "openaps": {
    "suggested": {
      "bg": 68, 
      "temp": "absolute", 
      "snoozeBG": 150, 
      "timestamp": "2017-04-24T01:06:19.890Z", 
      "reason": "COB: 73, Dev: 53, BGI: -11.75, ISF: 100, Target: 80; Eventual BG 134 > 80 but Min. Delta -3.00 < Exp. Delta -0.4; setting current basal of 0.675 as temp", 
      "rate": 0.675, 
      "COB": 73, 
      "eventualBG": 134, 
      "duration": 30, 
      "tick": -3, 
      "IOB": 2.46
    }, 
    "iob": {
      "netbasalinsulin": 1.9, 
      "timestamp": "2017-04-24T01:02:20.000Z", 
      "activity": 0.0235, 
      "basaliob": 0.141, 
      "hightempinsulin": 2.3, 
      "bolussnooze": 1.832, 
      "iob": 2.46
    }, 
    "enacted": {
      "bg": 68, 
      "temp": "absolute", 
      "snoozeBG": 150, 
      "recieved": true, 
      "predBGs": {
        "COB": [
          68, 
          65, 
          62, 
          58, 
          55, 
          51, 
          46, 
          42, 
          39, 
          39, 
          39, 
          39, 
          39, 
          39, 
          39, 
          39, 
          39, 
          39, 
          39, 
          39, 
          39, 
          39, 
          39, 
          39, 
          39, 
          39, 
          39, 
          39, 
          39, 
          44, 
          50, 
          58, 
          65, 
          72, 
          79, 
          86, 
          93, 
          100, 
          107, 
          114, 
          120, 
          127, 
          134
        ], 
        "aCOB": [
          68, 
          66, 
          64, 
          62, 
          59, 
          56, 
          53, 
          50, 
          46, 
          42, 
          39, 
          39, 
          39, 
          39, 
          39, 
          39, 
          39, 
          39, 
          39, 
          39, 
          39, 
          39, 
          39, 
          40, 
          44, 
          48, 
          54, 
          59, 
          66, 
          72, 
          80, 
          87, 
          95, 
          103, 
          111, 
          119, 
          126, 
          134, 
          141, 
          149, 
          156, 
          164, 
          171
        ], 
        "IOB": [
          68, 
          64, 
          60, 
          54, 
          48, 
          40, 
          39, 
          39, 
          39, 
          39, 
          39, 
          39, 
          39
        ]
      }, 
      "rate": 0.675, 
      "reason": "COB: 73, Dev: 53, BGI: -11.75, ISF: 100, Target: 80; Eventual BG 134 > 80 but Min. Delta -3.00 < Exp. Delta -0.4; setting current basal of 0.675 as temp", 
      "COB": 73, 
      "eventualBG": 134, 
      "timestamp": "2017-04-24T01:07:26.490Z", 
      "duration": 30, 
      "tick": -3, 
      "IOB": 2.46
    }
  }, 
  "mmtune": {
    "scanDetails": [
      [
        null, 
        0, 
        -87.6
      ]
    ], 
    "timestamp": "2017-04-24T01:07:34.351Z"
  }
}