{
  "device": "openaps://indy-ex2", 
  "pump": {
    "battery": {
      "status": "normal", 
      "voltage": 1.51
    }, 
    "status": {
      "status": "normal", 
      "timestamp": "2017-04-28T07:06:28.669Z", 
      "bolusing": false, 
      "suspended": false
    }, 
    "reservoir": 77.85, 
    "clock": "2017-04-28T00:06:26-07:00"
  }, 
  "uploader": {
    "battery": 68, 
    "batteryVoltage": 3861
  }, 
  "openaps": {
    "suggested": {
      "bg": 136, 
      "temp": "absolute", 
      "snoozeBG": 134, 
      "timestamp": "2017-04-28T07:09:35.811Z", 
      "predBGs": {
        "IOB": [
          136, 
          139, 
          142, 
          144, 
          146, 
          148, 
          149, 
          149, 
          149, 
          149, 
          148, 
          146, 
          144, 
          142, 
          139, 
          137, 
          134, 
          132, 
          129, 
          127, 
          125, 
          123, 
          121, 
          119, 
          117, 
          116, 
          114, 
          113, 
          112, 
          111, 
          110, 
          110, 
          109, 
          109, 
          108
        ]
      }, 
      "reason": "COB: 0, Dev: 27, BGI: -0.9, ISF: 90, Target: 98; Eventual BG 134 >= 98, temp 1.95 >~ req 1.95U/hr", 
      "COB": 0, 
      "eventualBG": 134, 
      "tick": "+5", 
      "IOB": 0.327
    }, 
    "iob": {
      "netbasalinsulin": 0.9, 
      "timestamp": "2017-04-28T07:06:26.000Z", 
      "activity": 0.002, 
      "basaliob": 0.327, 
      "hightempinsulin": 1.2, 
      "bolussnooze": 0, 
      "iob": 0.327
    }, 
    "enacted": {
      "bg": 109, 
      "temp": "absolute", 
      "snoozeBG": 98, 
      "recieved": true, 
      "rate": 1.35, 
      "reason": "COB: 1, Dev: 2, BGI: -2.31, ISF: 91, Target: 98; Eventual BG 102 >= 98, 7m@0.025 = 0.003 > req 0+20%. Setting temp basal of 1.35U/hr", 
      "COB": 1, 
      "eventualBG": 102, 
      "timestamp": "2017-04-28T06:16:15.845Z", 
      "duration": 30, 
      "tick": -1, 
      "IOB": 0.142
    }
  }, 
  "mmtune": {
    "scanDetails": [
      [
        null, 
        0, 
        -80
      ]
    ], 
    "timestamp": "2017-04-28T07:09:43.831Z"
  }
}