{
  "device": "openaps://indy-ex2", 
  "pump": {
    "battery": {
      "status": "normal", 
      "voltage": 1.42
    }, 
    "status": {
      "status": "normal", 
      "timestamp": "2017-04-08T08:27:28.614Z", 
      "bolusing": false, 
      "suspended": false
    }, 
    "reservoir": 92.9, 
    "clock": "2017-04-08T01:27:18-07:00"
  }, 
  "uploader": {
    "battery": 67, 
    "batteryVoltage": 3851
  }, 
  "openaps": {
    "suggested": {
      "bg": 58, 
      "temp": "absolute", 
      "snoozeBG": 104, 
      "timestamp": "2017-04-08T08:31:14.617Z", 
      "predBGs": {
        "COB": [
          58, 
          62, 
          66, 
          70, 
          75, 
          80, 
          86, 
          92, 
          98, 
          104, 
          110, 
          116, 
          122, 
          129, 
          135, 
          141, 
          147, 
          152, 
          158, 
          163, 
          167, 
          171, 
          175, 
          178, 
          180, 
          182, 
          184, 
          186, 
          188, 
          189, 
          190, 
          191, 
          192, 
          193, 
          193, 
          194
        ], 
        "aCOB": [
          58, 
          67, 
          75, 
          83, 
          90, 
          97, 
          103, 
          109, 
          114, 
          118, 
          122, 
          126, 
          131, 
          135, 
          140, 
          144, 
          149, 
          153, 
          157, 
          161, 
          165, 
          169, 
          172, 
          175, 
          177, 
          180, 
          182, 
          183, 
          185, 
          186, 
          187, 
          188, 
          189, 
          190, 
          190, 
          191, 
          191, 
          191, 
          191, 
          192
        ], 
        "IOB": [
          58, 
          62, 
          65, 
          69, 
          73, 
          78, 
          82, 
          87, 
          92, 
          96, 
          101, 
          105, 
          109, 
          114, 
          118, 
          123, 
          127, 
          132, 
          136, 
          140, 
          144, 
          147, 
          151, 
          154, 
          156, 
          158, 
          160, 
          162, 
          164, 
          165, 
          166, 
          167, 
          168, 
          169, 
          169, 
          170
        ]
      }, 
      "reason": "COB: 6, Dev: -14, BGI: -0.09, ISF: 86, Target: 96; BG 58<73, but 22m left and 0 ~ req 0U/hr: no action required", 
      "COB": 6, 
      "eventualBG": 194, 
      "tick": "+0", 
      "IOB": -0.698
    }, 
    "iob": {
      "netbasalinsulin": -0.1, 
      "timestamp": "2017-04-08T08:27:18.000Z", 
      "activity": 0.0002, 
      "basaliob": -0.698, 
      "hightempinsulin": 0.9, 
      "bolussnooze": 0, 
      "iob": -0.698
    }, 
    "enacted": {
      "bg": 63, 
      "temp": "absolute", 
      "snoozeBG": 94, 
      "recieved": true, 
      "rate": 0, 
      "reason": "COB: 0, Dev: -16, BGI: -0.99, ISF: 86, Target: 96; BG 63<73", 
      "COB": 0, 
      "eventualBG": 94, 
      "timestamp": "2017-04-08T08:20:55.788Z", 
      "duration": 30, 
      "tick": -5, 
      "IOB": -0.54
    }
  }, 
  "mmtune": {
    "scanDetails": [
      [
        null, 
        0, 
        -87.2
      ]
    ], 
    "timestamp": "2017-04-08T08:31:22.487Z"
  }
}